[
  {
    "id": 1,
    "first_name": "Fabe",
    "last_name": "Garoghan",
    "email": "fgaroghan0@nytimes.com",
    "gender": "Male",
    "Job-title": "Account Representative I"
  },
  {
    "id": 2,
    "first_name": "Phedra",
    "last_name": "Condie",
    "email": "pcondie1@gmpg.org",
    "gender": "Female",
    "Job-title": "Senior Editor"
  },
  {
    "id": 3,
    "first_name": "Padriac",
    "last_name": "Crimpe",
    "email": "pcrimpe2@indiegogo.com",
    "gender": "Male",
    "Job-title": "Technical Writer"
  },
  {
    "id": 4,
    "first_name": "Martica",
    "last_name": "Fishburn",
    "email": "mfishburn3@slashdot.org",
    "gender": "Female",
    "Job-title": "VP Sales"
  },
  {
    "id": 5,
    "first_name": "Prince",
    "last_name": "Gilffilland",
    "email": "pgilffilland4@cornell.edu",
    "gender": "Male",
    "Job-title": "Web Designer II"
  },
  {
    "id": 6,
    "first_name": "Tiena",
    "last_name": "Colston",
    "email": "tcolston5@thetimes.co.uk",
    "gender": "Female",
    "Job-title": "Junior Executive"
  },
  {
    "id": 7,
    "first_name": "Sarena",
    "last_name": "McDirmid",
    "email": "smcdirmid6@telegraph.co.uk",
    "gender": "Female",
    "Job-title": "Community Outreach Specialist"
  },
  {
    "id": 8,
    "first_name": "Gunar",
    "last_name": "Culpan",
    "email": "gculpan7@census.gov",
    "gender": "Male",
    "Job-title": "Budget/Accounting Analyst I"
  },
  {
    "id": 9,
    "first_name": "Laetitia",
    "last_name": "Stode",
    "email": "lstode8@deviantart.com",
    "gender": "Female",
    "Job-title": "Nurse"
  },
  {
    "id": 10,
    "first_name": "Artemas",
    "last_name": "Blood",
    "email": "ablood9@tripadvisor.com",
    "gender": "Genderfluid",
    "Job-title": "Teacher"
  },
  {
    "id": 11,
    "first_name": "Meyer",
    "last_name": "Clougher",
    "email": "mcloughera@techcrunch.com",
    "gender": "Male",
    "Job-title": "Research Associate"
  },
  {
    "id": 12,
    "first_name": "Ambrosi",
    "last_name": "Piddocke",
    "email": "apiddockeb@chron.com",
    "gender": "Male",
    "Job-title": "Physical Therapy Assistant"
  },
  {
    "id": 13,
    "first_name": "Caesar",
    "last_name": "Muslim",
    "email": "cmuslimc@sciencedaily.com",
    "gender": "Male",
    "Job-title": "Senior Editor"
  },
  {
    "id": 14,
    "first_name": "Ancell",
    "last_name": "Ziemens",
    "email": "aziemensd@fc2.com",
    "gender": "Male",
    "Job-title": "Nurse"
  },
  {
    "id": 15,
    "first_name": "Natal",
    "last_name": "Selliman",
    "email": "nsellimane@mayoclinic.com",
    "gender": "Male",
    "Job-title": "Research Assistant IV"
  },
  {
    "id": 16,
    "first_name": "Veriee",
    "last_name": "Grunwald",
    "email": "vgrunwaldf@guardian.co.uk",
    "gender": "Female",
    "Job-title": "Pharmacist"
  },
  {
    "id": 17,
    "first_name": "Nanni",
    "last_name": "Von Helmholtz",
    "email": "nvonhelmholtzg@buzzfeed.com",
    "gender": "Female",
    "Job-title": "Programmer Analyst I"
  },
  {
    "id": 18,
    "first_name": "Darcie",
    "last_name": "Leonardi",
    "email": "dleonardih@blogspot.com",
    "gender": "Female",
    "Job-title": "Payment Adjustment Coordinator"
  },
  {
    "id": 19,
    "first_name": "Sydel",
    "last_name": "Pesik",
    "email": "spesiki@istockphoto.com",
    "gender": "Female",
    "Job-title": "Safety Technician III"
  },
  {
    "id": 20,
    "first_name": "Hinze",
    "last_name": "Ianson",
    "email": "hiansonj@booking.com",
    "gender": "Male",
    "Job-title": "Automation Specialist II"
  },
  {
    "id": 21,
    "first_name": "Siffre",
    "last_name": "Wheatley",
    "email": "swheatleyk@boston.com",
    "gender": "Male",
    "Job-title": "Teacher"
  },
  {
    "id": 22,
    "first_name": "Edee",
    "last_name": "Dongles",
    "email": "edonglesl@tumblr.com",
    "gender": "Female",
    "Job-title": "Quality Control Specialist"
  },
  {
    "id": 23,
    "first_name": "Ronda",
    "last_name": "Brabin",
    "email": "rbrabinm@oaic.gov.au",
    "gender": "Non-binary",
    "Job-title": "Automation Specialist IV"
  },
  {
    "id": 24,
    "first_name": "Angeline",
    "last_name": "Silliman",
    "email": "asillimann@bigcartel.com",
    "gender": "Female",
    "Job-title": "Nuclear Power Engineer"
  },
  {
    "id": 25,
    "first_name": "Georgie",
    "last_name": "McDuff",
    "email": "gmcduffo@ehow.com",
    "gender": "Female",
    "Job-title": "Legal Assistant"
  },
  {
    "id": 26,
    "first_name": "Prudi",
    "last_name": "Gowanson",
    "email": "pgowansonp@squidoo.com",
    "gender": "Female",
    "Job-title": "Compensation Analyst"
  },
  {
    "id": 27,
    "first_name": "Fredelia",
    "last_name": "Woolner",
    "email": "fwoolnerq@army.mil",
    "gender": "Female",
    "Job-title": "Marketing Assistant"
  },
  {
    "id": 28,
    "first_name": "Janette",
    "last_name": "Earle",
    "email": "jearler@youtu.be",
    "gender": "Female",
    "Job-title": "Senior Sales Associate"
  },
  {
    "id": 29,
    "first_name": "Gordon",
    "last_name": "Barnewall",
    "email": "gbarnewalls@ihg.com",
    "gender": "Male",
    "Job-title": "Dental Hygienist"
  },
  {
    "id": 30,
    "first_name": "Trevar",
    "last_name": "Stonestreet",
    "email": "tstonestreett@devhub.com",
    "gender": "Male",
    "Job-title": "Graphic Designer"
  },
  {
    "id": 31,
    "first_name": "Mariam",
    "last_name": "Thunderchief",
    "email": "mthunderchiefu@indiegogo.com",
    "gender": "Female",
    "Job-title": "Electrical Engineer"
  },
  {
    "id": 32,
    "first_name": "Celesta",
    "last_name": "Ashfield",
    "email": "cashfieldv@fc2.com",
    "gender": "Female",
    "Job-title": "Environmental Specialist"
  },
  {
    "id": 33,
    "first_name": "Madison",
    "last_name": "Teare",
    "email": "mtearew@wikia.com",
    "gender": "Male",
    "Job-title": "Payment Adjustment Coordinator"
  },
  {
    "id": 34,
    "first_name": "Allyson",
    "last_name": "Damant",
    "email": "adamantx@tiny.cc",
    "gender": "Female",
    "Job-title": "Web Designer I"
  },
  {
    "id": 35,
    "first_name": "Zea",
    "last_name": "De la Eglise",
    "email": "zdelaeglisey@yale.edu",
    "gender": "Genderfluid",
    "Job-title": "Associate Professor"
  },
  {
    "id": 36,
    "first_name": "Jude",
    "last_name": "Soot",
    "email": "jsootz@slideshare.net",
    "gender": "Male",
    "Job-title": "Librarian"
  },
  {
    "id": 37,
    "first_name": "Rena",
    "last_name": "Thorne",
    "email": "rthorne10@multiply.com",
    "gender": "Female",
    "Job-title": "Automation Specialist I"
  },
  {
    "id": 38,
    "first_name": "Gil",
    "last_name": "Uridge",
    "email": "guridge11@deviantart.com",
    "gender": "Male",
    "Job-title": "Chemical Engineer"
  },
  {
    "id": 39,
    "first_name": "Elia",
    "last_name": "Bavage",
    "email": "ebavage12@taobao.com",
    "gender": "Male",
    "Job-title": "Marketing Manager"
  },
  {
    "id": 40,
    "first_name": "Allayne",
    "last_name": "Derkes",
    "email": "aderkes13@google.co.uk",
    "gender": "Male",
    "Job-title": "Budget/Accounting Analyst I"
  },
  {
    "id": 41,
    "first_name": "Flynn",
    "last_name": "Mettrick",
    "email": "fmettrick14@gizmodo.com",
    "gender": "Non-binary",
    "Job-title": "Analyst Programmer"
  },
  {
    "id": 42,
    "first_name": "Lauraine",
    "last_name": "McNelly",
    "email": "lmcnelly15@facebook.com",
    "gender": "Female",
    "Job-title": "VP Marketing"
  },
  {
    "id": 43,
    "first_name": "Lotti",
    "last_name": "Amoore",
    "email": "lamoore16@google.fr",
    "gender": "Female",
    "Job-title": "Nurse Practicioner"
  },
  {
    "id": 44,
    "first_name": "Wendy",
    "last_name": "Bapty",
    "email": "wbapty17@google.es",
    "gender": "Female",
    "Job-title": "Health Coach IV"
  },
  {
    "id": 45,
    "first_name": "Cassy",
    "last_name": "Bain",
    "email": "cbain18@rakuten.co.jp",
    "gender": "Female",
    "Job-title": "Senior Quality Engineer"
  },
  {
    "id": 46,
    "first_name": "Phillie",
    "last_name": "Mate",
    "email": "pmate19@about.me",
    "gender": "Female",
    "Job-title": "Design Engineer"
  },
  {
    "id": 47,
    "first_name": "Melesa",
    "last_name": "Gascard",
    "email": "mgascard1a@cnbc.com",
    "gender": "Female",
    "Job-title": "Quality Control Specialist"
  },
  {
    "id": 48,
    "first_name": "Annalee",
    "last_name": "Eburah",
    "email": "aeburah1b@accuweather.com",
    "gender": "Female",
    "Job-title": "Legal Assistant"
  },
  {
    "id": 49,
    "first_name": "Tory",
    "last_name": "Bracher",
    "email": "tbracher1c@google.it",
    "gender": "Female",
    "Job-title": "Senior Developer"
  },
  {
    "id": 50,
    "first_name": "Kamila",
    "last_name": "Devin",
    "email": "kdevin1d@phpbb.com",
    "gender": "Female",
    "Job-title": "Structural Engineer"
  },
  {
    "id": 51,
    "first_name": "Derward",
    "last_name": "Iacopetti",
    "email": "diacopetti1e@ameblo.jp",
    "gender": "Male",
    "Job-title": "Financial Analyst"
  },
  {
    "id": 52,
    "first_name": "Basile",
    "last_name": "Sandels",
    "email": "bsandels1f@ucoz.ru",
    "gender": "Male",
    "Job-title": "Business Systems Development Analyst"
  },
  {
    "id": 53,
    "first_name": "Sebastiano",
    "last_name": "Huddle",
    "email": "shuddle1g@usa.gov",
    "gender": "Male",
    "Job-title": "Design Engineer"
  },
  {
    "id": 54,
    "first_name": "Sammy",
    "last_name": "Forseith",
    "email": "sforseith1h@t-online.de",
    "gender": "Bigender",
    "Job-title": "Nurse Practicioner"
  },
  {
    "id": 55,
    "first_name": "Enoch",
    "last_name": "Stiffkins",
    "email": "estiffkins1i@abc.net.au",
    "gender": "Male",
    "Job-title": "Quality Engineer"
  },
  {
    "id": 56,
    "first_name": "Ingar",
    "last_name": "Pollastro",
    "email": "ipollastro1j@nbcnews.com",
    "gender": "Polygender",
    "Job-title": "Information Systems Manager"
  },
  {
    "id": 57,
    "first_name": "Davide",
    "last_name": "Dansie",
    "email": "ddansie1k@themeforest.net",
    "gender": "Male",
    "Job-title": "Mechanical Systems Engineer"
  },
  {
    "id": 58,
    "first_name": "Barney",
    "last_name": "Isgate",
    "email": "bisgate1l@discovery.com",
    "gender": "Male",
    "Job-title": "Internal Auditor"
  },
  {
    "id": 59,
    "first_name": "Tadd",
    "last_name": "Niche",
    "email": "tniche1m@addthis.com",
    "gender": "Male",
    "Job-title": "Budget/Accounting Analyst III"
  },
  {
    "id": 60,
    "first_name": "Temple",
    "last_name": "Andriveau",
    "email": "tandriveau1n@google.de",
    "gender": "Male",
    "Job-title": "Nurse Practicioner"
  },
  {
    "id": 61,
    "first_name": "Cesya",
    "last_name": "Mulvany",
    "email": "cmulvany1o@cloudflare.com",
    "gender": "Female",
    "Job-title": "VP Sales"
  },
  {
    "id": 62,
    "first_name": "Florentia",
    "last_name": "Parr",
    "email": "fparr1p@skyrock.com",
    "gender": "Female",
    "Job-title": "Systems Administrator IV"
  },
  {
    "id": 63,
    "first_name": "Agna",
    "last_name": "Concannon",
    "email": "aconcannon1q@digg.com",
    "gender": "Female",
    "Job-title": "Nurse"
  },
  {
    "id": 64,
    "first_name": "Osbourne",
    "last_name": "Duckering",
    "email": "oduckering1r@jimdo.com",
    "gender": "Male",
    "Job-title": "Physical Therapy Assistant"
  },
  {
    "id": 65,
    "first_name": "Grete",
    "last_name": "Deadman",
    "email": "gdeadman1s@github.com",
    "gender": "Female",
    "Job-title": "Analog Circuit Design manager"
  },
  {
    "id": 66,
    "first_name": "Christabella",
    "last_name": "MacVanamy",
    "email": "cmacvanamy1t@unc.edu",
    "gender": "Female",
    "Job-title": "Librarian"
  },
  {
    "id": 67,
    "first_name": "Marys",
    "last_name": "Giacobo",
    "email": "mgiacobo1u@ocn.ne.jp",
    "gender": "Female",
    "Job-title": "Registered Nurse"
  },
  {
    "id": 68,
    "first_name": "Kay",
    "last_name": "Roome",
    "email": "kroome1v@nature.com",
    "gender": "Female",
    "Job-title": "Administrative Assistant IV"
  },
  {
    "id": 69,
    "first_name": "Cristen",
    "last_name": "Gauler",
    "email": "cgauler1w@answers.com",
    "gender": "Female",
    "Job-title": "Teacher"
  },
  {
    "id": 70,
    "first_name": "Kerwin",
    "last_name": "Laverock",
    "email": "klaverock1x@stanford.edu",
    "gender": "Male",
    "Job-title": "Software Engineer II"
  },
  {
    "id": 71,
    "first_name": "Matthias",
    "last_name": "Whitlow",
    "email": "mwhitlow1y@shutterfly.com",
    "gender": "Male",
    "Job-title": "Marketing Manager"
  },
  {
    "id": 72,
    "first_name": "Carlo",
    "last_name": "Screase",
    "email": "cscrease1z@nationalgeographic.com",
    "gender": "Male",
    "Job-title": "Sales Associate"
  },
  {
    "id": 73,
    "first_name": "Lloyd",
    "last_name": "Fawthrop",
    "email": "lfawthrop20@archive.org",
    "gender": "Male",
    "Job-title": "Clinical Specialist"
  },
  {
    "id": 74,
    "first_name": "Myrtle",
    "last_name": "Mottershead",
    "email": "mmottershead21@surveymonkey.com",
    "gender": "Female",
    "Job-title": "Paralegal"
  },
  {
    "id": 75,
    "first_name": "Hugibert",
    "last_name": "Kirtley",
    "email": "hkirtley22@nydailynews.com",
    "gender": "Male",
    "Job-title": "Software Test Engineer III"
  },
  {
    "id": 76,
    "first_name": "Jocko",
    "last_name": "Dows",
    "email": "jdows23@hibu.com",
    "gender": "Male",
    "Job-title": "Occupational Therapist"
  },
  {
    "id": 77,
    "first_name": "Tully",
    "last_name": "Farthin",
    "email": "tfarthin24@soup.io",
    "gender": "Male",
    "Job-title": "Junior Executive"
  },
  {
    "id": 78,
    "first_name": "Con",
    "last_name": "Farrey",
    "email": "cfarrey25@google.com.au",
    "gender": "Female",
    "Job-title": "Senior Cost Accountant"
  },
  {
    "id": 79,
    "first_name": "Clyde",
    "last_name": "Waiton",
    "email": "cwaiton26@cargocollective.com",
    "gender": "Male",
    "Job-title": "Web Developer II"
  },
  {
    "id": 80,
    "first_name": "Molli",
    "last_name": "Arrundale",
    "email": "marrundale27@bravesites.com",
    "gender": "Female",
    "Job-title": "Chief Design Engineer"
  },
  {
    "id": 81,
    "first_name": "Cobby",
    "last_name": "Iwanowicz",
    "email": "ciwanowicz28@shutterfly.com",
    "gender": "Male",
    "Job-title": "Business Systems Development Analyst"
  },
  {
    "id": 82,
    "first_name": "Kay",
    "last_name": "Sangwine",
    "email": "ksangwine29@answers.com",
    "gender": "Female",
    "Job-title": "Sales Associate"
  },
  {
    "id": 83,
    "first_name": "Lucio",
    "last_name": "Arzu",
    "email": "larzu2a@hud.gov",
    "gender": "Male",
    "Job-title": "Product Engineer"
  },
  {
    "id": 84,
    "first_name": "Nappie",
    "last_name": "Pollok",
    "email": "npollok2b@apache.org",
    "gender": "Male",
    "Job-title": "Product Engineer"
  },
  {
    "id": 85,
    "first_name": "Eleni",
    "last_name": "Bute",
    "email": "ebute2c@tuttocitta.it",
    "gender": "Female",
    "Job-title": "Financial Analyst"
  },
  {
    "id": 86,
    "first_name": "Spenser",
    "last_name": "Isted",
    "email": "sisted2d@xing.com",
    "gender": "Male",
    "Job-title": "Senior Cost Accountant"
  },
  {
    "id": 87,
    "first_name": "Sorcha",
    "last_name": "Blampy",
    "email": "sblampy2e@blog.com",
    "gender": "Female",
    "Job-title": "Civil Engineer"
  },
  {
    "id": 88,
    "first_name": "Sigismondo",
    "last_name": "Burner",
    "email": "sburner2f@blogger.com",
    "gender": "Male",
    "Job-title": "Database Administrator IV"
  },
  {
    "id": 89,
    "first_name": "Linnet",
    "last_name": "Curlis",
    "email": "lcurlis2g@exblog.jp",
    "gender": "Female",
    "Job-title": "Senior Financial Analyst"
  },
  {
    "id": 90,
    "first_name": "Sharla",
    "last_name": "Foxen",
    "email": "sfoxen2h@google.fr",
    "gender": "Female",
    "Job-title": "Computer Systems Analyst IV"
  },
  {
    "id": 91,
    "first_name": "Lorant",
    "last_name": "Hackworth",
    "email": "lhackworth2i@vistaprint.com",
    "gender": "Male",
    "Job-title": "Software Engineer IV"
  },
  {
    "id": 92,
    "first_name": "Cathryn",
    "last_name": "Alden",
    "email": "calden2j@weather.com",
    "gender": "Female",
    "Job-title": "Nurse"
  },
  {
    "id": 93,
    "first_name": "Seth",
    "last_name": "Fintoph",
    "email": "sfintoph2k@businessweek.com",
    "gender": "Agender",
    "Job-title": "Teacher"
  },
  {
    "id": 94,
    "first_name": "Giuditta",
    "last_name": "Abela",
    "email": "gabela2l@dedecms.com",
    "gender": "Female",
    "Job-title": "Accounting Assistant IV"
  },
  {
    "id": 95,
    "first_name": "Jacinthe",
    "last_name": "Pellett",
    "email": "jpellett2m@zimbio.com",
    "gender": "Female",
    "Job-title": "Budget/Accounting Analyst IV"
  },
  {
    "id": 96,
    "first_name": "Antonella",
    "last_name": "Eye",
    "email": "aeye2n@auda.org.au",
    "gender": "Genderqueer",
    "Job-title": "Assistant Media Planner"
  },
  {
    "id": 97,
    "first_name": "Gregg",
    "last_name": "Feavyour",
    "email": "gfeavyour2o@google.com.hk",
    "gender": "Male",
    "Job-title": "Associate Professor"
  },
  {
    "id": 98,
    "first_name": "Christos",
    "last_name": "Jarnell",
    "email": "cjarnell2p@youku.com",
    "gender": "Male",
    "Job-title": "Desktop Support Technician"
  },
  {
    "id": 99,
    "first_name": "Urbano",
    "last_name": "Roe",
    "email": "uroe2q@instagram.com",
    "gender": "Male",
    "Job-title": "Editor"
  },
  {
    "id": 100,
    "first_name": "Alic",
    "last_name": "Domone",
    "email": "adomone2r@ted.com",
    "gender": "Male",
    "Job-title": "Community Outreach Specialist"
  },
  {
    "id": 101,
    "first_name": "Talyah",
    "last_name": "Jeanel",
    "email": "tjeanel2s@gizmodo.com",
    "gender": "Female",
    "Job-title": "Graphic Designer"
  },
  {
    "id": 102,
    "first_name": "Lucinda",
    "last_name": "Massy",
    "email": "lmassy2t@goo.ne.jp",
    "gender": "Female",
    "Job-title": "Programmer Analyst IV"
  },
  {
    "id": 103,
    "first_name": "Rollo",
    "last_name": "Baird",
    "email": "rbaird2u@disqus.com",
    "gender": "Male",
    "Job-title": "Senior Financial Analyst"
  },
  {
    "id": 104,
    "first_name": "Prent",
    "last_name": "Basnett",
    "email": "pbasnett2v@google.com",
    "gender": "Male",
    "Job-title": "Desktop Support Technician"
  },
  {
    "id": 105,
    "first_name": "Danila",
    "last_name": "Twigley",
    "email": "dtwigley2w@hugedomains.com",
    "gender": "Female",
    "Job-title": "Sales Associate"
  },
  {
    "id": 106,
    "first_name": "Grata",
    "last_name": "Sherrin",
    "email": "gsherrin2x@springer.com",
    "gender": "Female",
    "Job-title": "Software Engineer III"
  },
  {
    "id": 107,
    "first_name": "Lucius",
    "last_name": "Hedges",
    "email": "lhedges2y@state.tx.us",
    "gender": "Male",
    "Job-title": "Safety Technician IV"
  },
  {
    "id": 108,
    "first_name": "Ibbie",
    "last_name": "Pritty",
    "email": "ipritty2z@google.de",
    "gender": "Female",
    "Job-title": "Marketing Assistant"
  },
  {
    "id": 109,
    "first_name": "Edwina",
    "last_name": "Jocic",
    "email": "ejocic30@photobucket.com",
    "gender": "Female",
    "Job-title": "Account Executive"
  },
  {
    "id": 110,
    "first_name": "Lewie",
    "last_name": "Spikings",
    "email": "lspikings31@wikipedia.org",
    "gender": "Male",
    "Job-title": "Statistician III"
  },
  {
    "id": 111,
    "first_name": "Gigi",
    "last_name": "Marples",
    "email": "gmarples32@npr.org",
    "gender": "Female",
    "Job-title": "Research Assistant IV"
  },
  {
    "id": 112,
    "first_name": "Sanderson",
    "last_name": "Darville",
    "email": "sdarville33@trellian.com",
    "gender": "Male",
    "Job-title": "Accountant III"
  },
  {
    "id": 113,
    "first_name": "Curt",
    "last_name": "Spoure",
    "email": "cspoure34@bing.com",
    "gender": "Male",
    "Job-title": "Director of Sales"
  },
  {
    "id": 114,
    "first_name": "Mel",
    "last_name": "Airdrie",
    "email": "mairdrie35@odnoklassniki.ru",
    "gender": "Female",
    "Job-title": "Speech Pathologist"
  },
  {
    "id": 115,
    "first_name": "Jessamine",
    "last_name": "Kirke",
    "email": "jkirke36@twitpic.com",
    "gender": "Female",
    "Job-title": "Senior Sales Associate"
  },
  {
    "id": 116,
    "first_name": "Marjy",
    "last_name": "Gleader",
    "email": "mgleader37@nasa.gov",
    "gender": "Female",
    "Job-title": "Geological Engineer"
  },
  {
    "id": 117,
    "first_name": "Sharlene",
    "last_name": "Hackley",
    "email": "shackley38@nps.gov",
    "gender": "Female",
    "Job-title": "Human Resources Assistant IV"
  },
  {
    "id": 118,
    "first_name": "Mattheus",
    "last_name": "Jaggar",
    "email": "mjaggar39@amazon.de",
    "gender": "Male",
    "Job-title": "Human Resources Manager"
  },
  {
    "id": 119,
    "first_name": "Jud",
    "last_name": "Cordeix",
    "email": "jcordeix3a@narod.ru",
    "gender": "Male",
    "Job-title": "Research Associate"
  },
  {
    "id": 120,
    "first_name": "Manolo",
    "last_name": "Pellingar",
    "email": "mpellingar3b@g.co",
    "gender": "Male",
    "Job-title": "Pharmacist"
  },
  {
    "id": 121,
    "first_name": "Kris",
    "last_name": "Dulany",
    "email": "kdulany3c@ucsd.edu",
    "gender": "Genderqueer",
    "Job-title": "Nurse Practicioner"
  },
  {
    "id": 122,
    "first_name": "Ody",
    "last_name": "Malpas",
    "email": "omalpas3d@reverbnation.com",
    "gender": "Male",
    "Job-title": "Recruiter"
  },
  {
    "id": 123,
    "first_name": "Perle",
    "last_name": "Latchmore",
    "email": "platchmore3e@bandcamp.com",
    "gender": "Female",
    "Job-title": "Graphic Designer"
  },
  {
    "id": 124,
    "first_name": "Raf",
    "last_name": "McCloch",
    "email": "rmccloch3f@google.com",
    "gender": "Female",
    "Job-title": "Social Worker"
  },
  {
    "id": 125,
    "first_name": "Kennie",
    "last_name": "Skittreal",
    "email": "kskittreal3g@hp.com",
    "gender": "Male",
    "Job-title": "Paralegal"
  },
  {
    "id": 126,
    "first_name": "Maje",
    "last_name": "Baldrey",
    "email": "mbaldrey3h@tamu.edu",
    "gender": "Male",
    "Job-title": "Research Nurse"
  },
  {
    "id": 127,
    "first_name": "Herve",
    "last_name": "Caunce",
    "email": "hcaunce3i@comcast.net",
    "gender": "Male",
    "Job-title": "VP Quality Control"
  },
  {
    "id": 128,
    "first_name": "Rosa",
    "last_name": "Carlino",
    "email": "rcarlino3j@com.com",
    "gender": "Female",
    "Job-title": "Legal Assistant"
  },
  {
    "id": 129,
    "first_name": "Levey",
    "last_name": "Ayliffe",
    "email": "layliffe3k@state.gov",
    "gender": "Male",
    "Job-title": "Legal Assistant"
  },
  {
    "id": 130,
    "first_name": "Guthrey",
    "last_name": "Crewther",
    "email": "gcrewther3l@uol.com.br",
    "gender": "Male",
    "Job-title": "Environmental Specialist"
  },
  {
    "id": 131,
    "first_name": "Hilliard",
    "last_name": "Chesney",
    "email": "hchesney3m@sbwire.com",
    "gender": "Male",
    "Job-title": "Recruiter"
  },
  {
    "id": 132,
    "first_name": "Greggory",
    "last_name": "Cokayne",
    "email": "gcokayne3n@usgs.gov",
    "gender": "Male",
    "Job-title": "Database Administrator II"
  },
  {
    "id": 133,
    "first_name": "Nessie",
    "last_name": "Blenkinsop",
    "email": "nblenkinsop3o@usnews.com",
    "gender": "Female",
    "Job-title": "Help Desk Technician"
  },
  {
    "id": 134,
    "first_name": "Aggie",
    "last_name": "MacCosty",
    "email": "amaccosty3p@sciencedaily.com",
    "gender": "Female",
    "Job-title": "Geological Engineer"
  },
  {
    "id": 135,
    "first_name": "Delmore",
    "last_name": "Sapp",
    "email": "dsapp3q@discovery.com",
    "gender": "Male",
    "Job-title": "Analyst Programmer"
  },
  {
    "id": 136,
    "first_name": "Buck",
    "last_name": "Gilardoni",
    "email": "bgilardoni3r@google.com.br",
    "gender": "Male",
    "Job-title": "Civil Engineer"
  },
  {
    "id": 137,
    "first_name": "Madelle",
    "last_name": "Ferriby",
    "email": "mferriby3s@creativecommons.org",
    "gender": "Female",
    "Job-title": "Safety Technician I"
  },
  {
    "id": 138,
    "first_name": "Currie",
    "last_name": "Manwell",
    "email": "cmanwell3t@chron.com",
    "gender": "Male",
    "Job-title": "General Manager"
  },
  {
    "id": 139,
    "first_name": "Carlye",
    "last_name": "Huntingdon",
    "email": "chuntingdon3u@ow.ly",
    "gender": "Female",
    "Job-title": "Senior Cost Accountant"
  },
  {
    "id": 140,
    "first_name": "Christabel",
    "last_name": "Bartosek",
    "email": "cbartosek3v@nasa.gov",
    "gender": "Female",
    "Job-title": "Software Consultant"
  },
  {
    "id": 141,
    "first_name": "Hali",
    "last_name": "Gailor",
    "email": "hgailor3w@newyorker.com",
    "gender": "Female",
    "Job-title": "Senior Developer"
  },
  {
    "id": 142,
    "first_name": "Fritz",
    "last_name": "Kick",
    "email": "fkick3x@usatoday.com",
    "gender": "Male",
    "Job-title": "Social Worker"
  },
  {
    "id": 143,
    "first_name": "Burg",
    "last_name": "Bidewel",
    "email": "bbidewel3y@google.it",
    "gender": "Male",
    "Job-title": "Assistant Manager"
  },
  {
    "id": 144,
    "first_name": "Cyril",
    "last_name": "Middis",
    "email": "cmiddis3z@ehow.com",
    "gender": "Male",
    "Job-title": "Media Manager II"
  },
  {
    "id": 145,
    "first_name": "Oneida",
    "last_name": "Sarvar",
    "email": "osarvar40@naver.com",
    "gender": "Female",
    "Job-title": "Health Coach III"
  },
  {
    "id": 146,
    "first_name": "Petr",
    "last_name": "Stirland",
    "email": "pstirland41@trellian.com",
    "gender": "Male",
    "Job-title": "Developer I"
  },
  {
    "id": 147,
    "first_name": "Fidel",
    "last_name": "Wallace",
    "email": "fwallace42@parallels.com",
    "gender": "Male",
    "Job-title": "Junior Executive"
  },
  {
    "id": 148,
    "first_name": "Gilligan",
    "last_name": "Grout",
    "email": "ggrout43@uol.com.br",
    "gender": "Polygender",
    "Job-title": "Marketing Manager"
  },
  {
    "id": 149,
    "first_name": "Mufinella",
    "last_name": "Alsobrook",
    "email": "malsobrook44@geocities.jp",
    "gender": "Female",
    "Job-title": "GIS Technical Architect"
  },
  {
    "id": 150,
    "first_name": "Christiana",
    "last_name": "Firby",
    "email": "cfirby45@wikispaces.com",
    "gender": "Female",
    "Job-title": "Environmental Specialist"
  },
  {
    "id": 151,
    "first_name": "Clemens",
    "last_name": "Rawsthorn",
    "email": "crawsthorn46@feedburner.com",
    "gender": "Male",
    "Job-title": "VP Product Management"
  },
  {
    "id": 152,
    "first_name": "Dorine",
    "last_name": "Bramble",
    "email": "dbramble47@cdbaby.com",
    "gender": "Genderfluid",
    "Job-title": "Administrative Assistant II"
  },
  {
    "id": 153,
    "first_name": "Maddalena",
    "last_name": "France",
    "email": "mfrance48@bigcartel.com",
    "gender": "Polygender",
    "Job-title": "Dental Hygienist"
  },
  {
    "id": 154,
    "first_name": "Giovanna",
    "last_name": "Malamore",
    "email": "gmalamore49@nih.gov",
    "gender": "Female",
    "Job-title": "Occupational Therapist"
  },
  {
    "id": 155,
    "first_name": "Georgeanne",
    "last_name": "Nehl",
    "email": "gnehl4a@sun.com",
    "gender": "Female",
    "Job-title": "Senior Quality Engineer"
  },
  {
    "id": 156,
    "first_name": "Lana",
    "last_name": "Myhill",
    "email": "lmyhill4b@google.nl",
    "gender": "Female",
    "Job-title": "Human Resources Manager"
  },
  {
    "id": 157,
    "first_name": "Calypso",
    "last_name": "Ollerenshaw",
    "email": "collerenshaw4c@xrea.com",
    "gender": "Female",
    "Job-title": "Chemical Engineer"
  },
  {
    "id": 158,
    "first_name": "Nelson",
    "last_name": "Kittel",
    "email": "nkittel4d@cyberchimps.com",
    "gender": "Male",
    "Job-title": "Librarian"
  },
  {
    "id": 159,
    "first_name": "Elianore",
    "last_name": "Seamarke",
    "email": "eseamarke4e@360.cn",
    "gender": "Female",
    "Job-title": "Assistant Media Planner"
  },
  {
    "id": 160,
    "first_name": "Maxy",
    "last_name": "Brideoke",
    "email": "mbrideoke4f@arizona.edu",
    "gender": "Male",
    "Job-title": "VP Accounting"
  },
  {
    "id": 161,
    "first_name": "Hermon",
    "last_name": "Hartles",
    "email": "hhartles4g@macromedia.com",
    "gender": "Male",
    "Job-title": "Engineer III"
  },
  {
    "id": 162,
    "first_name": "Rene",
    "last_name": "Keetch",
    "email": "rkeetch4h@list-manage.com",
    "gender": "Male",
    "Job-title": "Payment Adjustment Coordinator"
  },
  {
    "id": 163,
    "first_name": "Alexis",
    "last_name": "Pain",
    "email": "apain4i@bluehost.com",
    "gender": "Male",
    "Job-title": "Chief Design Engineer"
  },
  {
    "id": 164,
    "first_name": "Bethany",
    "last_name": "Sesser",
    "email": "bsesser4j@netscape.com",
    "gender": "Female",
    "Job-title": "Chief Design Engineer"
  },
  {
    "id": 165,
    "first_name": "Yolanthe",
    "last_name": "Giorgi",
    "email": "ygiorgi4k@nba.com",
    "gender": "Female",
    "Job-title": "Programmer Analyst III"
  },
  {
    "id": 166,
    "first_name": "Delia",
    "last_name": "Dever",
    "email": "ddever4l@tinypic.com",
    "gender": "Female",
    "Job-title": "Chief Design Engineer"
  },
  {
    "id": 167,
    "first_name": "Dilan",
    "last_name": "Bullant",
    "email": "dbullant4m@miibeian.gov.cn",
    "gender": "Male",
    "Job-title": "Human Resources Assistant I"
  },
  {
    "id": 168,
    "first_name": "Babette",
    "last_name": "Knappitt",
    "email": "bknappitt4n@ameblo.jp",
    "gender": "Female",
    "Job-title": "VP Product Management"
  },
  {
    "id": 169,
    "first_name": "Ivett",
    "last_name": "Buckel",
    "email": "ibuckel4o@dailymotion.com",
    "gender": "Polygender",
    "Job-title": "Professor"
  },
  {
    "id": 170,
    "first_name": "Umberto",
    "last_name": "Coltart",
    "email": "ucoltart4p@nsw.gov.au",
    "gender": "Male",
    "Job-title": "Office Assistant II"
  },
  {
    "id": 171,
    "first_name": "Rip",
    "last_name": "Lydden",
    "email": "rlydden4q@sina.com.cn",
    "gender": "Male",
    "Job-title": "Clinical Specialist"
  },
  {
    "id": 172,
    "first_name": "Ulrica",
    "last_name": "Boecke",
    "email": "uboecke4r@ustream.tv",
    "gender": "Female",
    "Job-title": "Account Executive"
  },
  {
    "id": 173,
    "first_name": "Kelsey",
    "last_name": "Cohn",
    "email": "kcohn4s@loc.gov",
    "gender": "Female",
    "Job-title": "Web Designer I"
  },
  {
    "id": 174,
    "first_name": "Ezra",
    "last_name": "Van Cassel",
    "email": "evancassel4t@gmpg.org",
    "gender": "Male",
    "Job-title": "Developer II"
  },
  {
    "id": 175,
    "first_name": "Vergil",
    "last_name": "Norkutt",
    "email": "vnorkutt4u@hao123.com",
    "gender": "Male",
    "Job-title": "Assistant Manager"
  },
  {
    "id": 176,
    "first_name": "Harwilll",
    "last_name": "Baulch",
    "email": "hbaulch4v@japanpost.jp",
    "gender": "Male",
    "Job-title": "Physical Therapy Assistant"
  },
  {
    "id": 177,
    "first_name": "Hartley",
    "last_name": "Brahm",
    "email": "hbrahm4w@ameblo.jp",
    "gender": "Male",
    "Job-title": "Quality Engineer"
  },
  {
    "id": 178,
    "first_name": "Jayne",
    "last_name": "Goodsall",
    "email": "jgoodsall4x@washington.edu",
    "gender": "Female",
    "Job-title": "Staff Scientist"
  },
  {
    "id": 179,
    "first_name": "Sharleen",
    "last_name": "Duthie",
    "email": "sduthie4y@delicious.com",
    "gender": "Female",
    "Job-title": "Systems Administrator I"
  },
  {
    "id": 180,
    "first_name": "Demetrius",
    "last_name": "Grzeskowski",
    "email": "dgrzeskowski4z@hostgator.com",
    "gender": "Male",
    "Job-title": "Social Worker"
  },
  {
    "id": 181,
    "first_name": "Hobard",
    "last_name": "Galilee",
    "email": "hgalilee50@mtv.com",
    "gender": "Male",
    "Job-title": "Payment Adjustment Coordinator"
  },
  {
    "id": 182,
    "first_name": "Pattie",
    "last_name": "Kubiak",
    "email": "pkubiak51@dmoz.org",
    "gender": "Male",
    "Job-title": "Geological Engineer"
  },
  {
    "id": 183,
    "first_name": "Obidiah",
    "last_name": "Huntley",
    "email": "ohuntley52@free.fr",
    "gender": "Male",
    "Job-title": "Research Assistant II"
  },
  {
    "id": 184,
    "first_name": "Wernher",
    "last_name": "Medford",
    "email": "wmedford53@dagondesign.com",
    "gender": "Male",
    "Job-title": "Nuclear Power Engineer"
  },
  {
    "id": 185,
    "first_name": "Sharia",
    "last_name": "Prover",
    "email": "sprover54@ask.com",
    "gender": "Female",
    "Job-title": "Operator"
  },
  {
    "id": 186,
    "first_name": "Herc",
    "last_name": "Gorner",
    "email": "hgorner55@vinaora.com",
    "gender": "Male",
    "Job-title": "Senior Sales Associate"
  },
  {
    "id": 187,
    "first_name": "Spenser",
    "last_name": "Klebes",
    "email": "sklebes56@dion.ne.jp",
    "gender": "Male",
    "Job-title": "Actuary"
  },
  {
    "id": 188,
    "first_name": "Jessalyn",
    "last_name": "Catterick",
    "email": "jcatterick57@wikia.com",
    "gender": "Female",
    "Job-title": "Budget/Accounting Analyst IV"
  },
  {
    "id": 189,
    "first_name": "Hurlee",
    "last_name": "Clapson",
    "email": "hclapson58@fda.gov",
    "gender": "Male",
    "Job-title": "Budget/Accounting Analyst III"
  },
  {
    "id": 190,
    "first_name": "Bordy",
    "last_name": "Bachnic",
    "email": "bbachnic59@zdnet.com",
    "gender": "Male",
    "Job-title": "Senior Developer"
  },
  {
    "id": 191,
    "first_name": "Darnell",
    "last_name": "Westley",
    "email": "dwestley5a@skyrock.com",
    "gender": "Male",
    "Job-title": "Human Resources Manager"
  },
  {
    "id": 192,
    "first_name": "Allard",
    "last_name": "Marling",
    "email": "amarling5b@nifty.com",
    "gender": "Male",
    "Job-title": "Paralegal"
  },
  {
    "id": 193,
    "first_name": "Mycah",
    "last_name": "Haitlie",
    "email": "mhaitlie5c@networksolutions.com",
    "gender": "Male",
    "Job-title": "Recruiting Manager"
  },
  {
    "id": 194,
    "first_name": "Liane",
    "last_name": "Knowlson",
    "email": "lknowlson5d@accuweather.com",
    "gender": "Female",
    "Job-title": "Senior Financial Analyst"
  },
  {
    "id": 195,
    "first_name": "Henderson",
    "last_name": "Endon",
    "email": "hendon5e@state.tx.us",
    "gender": "Male",
    "Job-title": "Librarian"
  },
  {
    "id": 196,
    "first_name": "Melloney",
    "last_name": "Petru",
    "email": "mpetru5f@merriam-webster.com",
    "gender": "Female",
    "Job-title": "Programmer II"
  },
  {
    "id": 197,
    "first_name": "Gregor",
    "last_name": "Dixon",
    "email": "gdixon5g@hp.com",
    "gender": "Male",
    "Job-title": "Tax Accountant"
  },
  {
    "id": 198,
    "first_name": "Bethany",
    "last_name": "Pinnion",
    "email": "bpinnion5h@reuters.com",
    "gender": "Female",
    "Job-title": "Analyst Programmer"
  },
  {
    "id": 199,
    "first_name": "Harmony",
    "last_name": "Symson",
    "email": "hsymson5i@creativecommons.org",
    "gender": "Female",
    "Job-title": "Speech Pathologist"
  },
  {
    "id": 200,
    "first_name": "Shoshanna",
    "last_name": "Agiolfinger",
    "email": "sagiolfinger5j@businesswire.com",
    "gender": "Female",
    "Job-title": "Staff Scientist"
  },
  {
    "id": 201,
    "first_name": "Shandy",
    "last_name": "Jollands",
    "email": "sjollands5k@admin.ch",
    "gender": "Female",
    "Job-title": "Senior Editor"
  },
  {
    "id": 202,
    "first_name": "Marsiella",
    "last_name": "O'Corren",
    "email": "mocorren5l@shareasale.com",
    "gender": "Female",
    "Job-title": "Web Developer I"
  },
  {
    "id": 203,
    "first_name": "Dehlia",
    "last_name": "Bromige",
    "email": "dbromige5m@adobe.com",
    "gender": "Female",
    "Job-title": "Biostatistician IV"
  },
  {
    "id": 204,
    "first_name": "Henri",
    "last_name": "Tosh",
    "email": "htosh5n@google.es",
    "gender": "Male",
    "Job-title": "Librarian"
  },
  {
    "id": 205,
    "first_name": "Donavon",
    "last_name": "Pringle",
    "email": "dpringle5o@g.co",
    "gender": "Male",
    "Job-title": "Clinical Specialist"
  },
  {
    "id": 206,
    "first_name": "Genovera",
    "last_name": "Strethill",
    "email": "gstrethill5p@soundcloud.com",
    "gender": "Female",
    "Job-title": "Human Resources Manager"
  },
  {
    "id": 207,
    "first_name": "Sheela",
    "last_name": "Sooper",
    "email": "ssooper5q@weather.com",
    "gender": "Female",
    "Job-title": "Nurse"
  },
  {
    "id": 208,
    "first_name": "Hildegarde",
    "last_name": "Gilfether",
    "email": "hgilfether5r@twitter.com",
    "gender": "Female",
    "Job-title": "Help Desk Technician"
  },
  {
    "id": 209,
    "first_name": "Scotti",
    "last_name": "Hugo",
    "email": "shugo5s@whitehouse.gov",
    "gender": "Male",
    "Job-title": "Help Desk Technician"
  },
  {
    "id": 210,
    "first_name": "Aline",
    "last_name": "Winchurch",
    "email": "awinchurch5t@instagram.com",
    "gender": "Female",
    "Job-title": "Accounting Assistant III"
  },
  {
    "id": 211,
    "first_name": "Marvin",
    "last_name": "Ambrogetti",
    "email": "mambrogetti5u@examiner.com",
    "gender": "Male",
    "Job-title": "Payment Adjustment Coordinator"
  },
  {
    "id": 212,
    "first_name": "Selie",
    "last_name": "Rehn",
    "email": "srehn5v@bravesites.com",
    "gender": "Female",
    "Job-title": "Structural Engineer"
  },
  {
    "id": 213,
    "first_name": "Alphonso",
    "last_name": "Leefe",
    "email": "aleefe5w@tamu.edu",
    "gender": "Male",
    "Job-title": "Account Executive"
  },
  {
    "id": 214,
    "first_name": "Carlie",
    "last_name": "Scrowton",
    "email": "cscrowton5x@spotify.com",
    "gender": "Female",
    "Job-title": "Clinical Specialist"
  },
  {
    "id": 215,
    "first_name": "Siffre",
    "last_name": "Alpin",
    "email": "salpin5y@howstuffworks.com",
    "gender": "Male",
    "Job-title": "Director of Sales"
  },
  {
    "id": 216,
    "first_name": "Jarrod",
    "last_name": "Ellesworthe",
    "email": "jellesworthe5z@tamu.edu",
    "gender": "Male",
    "Job-title": "Nurse"
  },
  {
    "id": 217,
    "first_name": "Kippar",
    "last_name": "Callum",
    "email": "kcallum60@slashdot.org",
    "gender": "Male",
    "Job-title": "Information Systems Manager"
  },
  {
    "id": 218,
    "first_name": "Antonella",
    "last_name": "Rentelll",
    "email": "arentelll61@taobao.com",
    "gender": "Female",
    "Job-title": "Research Assistant IV"
  },
  {
    "id": 219,
    "first_name": "Gayla",
    "last_name": "Ockleshaw",
    "email": "gockleshaw62@aboutads.info",
    "gender": "Female",
    "Job-title": "Chief Design Engineer"
  },
  {
    "id": 220,
    "first_name": "Iain",
    "last_name": "Petit",
    "email": "ipetit63@illinois.edu",
    "gender": "Male",
    "Job-title": "Associate Professor"
  },
  {
    "id": 221,
    "first_name": "Nolly",
    "last_name": "Grandin",
    "email": "ngrandin64@istockphoto.com",
    "gender": "Male",
    "Job-title": "Project Manager"
  },
  {
    "id": 222,
    "first_name": "Shamus",
    "last_name": "Treagust",
    "email": "streagust65@adobe.com",
    "gender": "Male",
    "Job-title": "Analog Circuit Design manager"
  },
  {
    "id": 223,
    "first_name": "Morey",
    "last_name": "De Courtney",
    "email": "mdecourtney66@smugmug.com",
    "gender": "Non-binary",
    "Job-title": "Chemical Engineer"
  },
  {
    "id": 224,
    "first_name": "Corette",
    "last_name": "Halworth",
    "email": "chalworth67@yahoo.co.jp",
    "gender": "Female",
    "Job-title": "Director of Sales"
  },
  {
    "id": 225,
    "first_name": "Adelaida",
    "last_name": "Spears",
    "email": "aspears68@usa.gov",
    "gender": "Female",
    "Job-title": "Research Assistant II"
  },
  {
    "id": 226,
    "first_name": "Jenny",
    "last_name": "Giovannardi",
    "email": "jgiovannardi69@bloglovin.com",
    "gender": "Female",
    "Job-title": "Chemical Engineer"
  },
  {
    "id": 227,
    "first_name": "Shane",
    "last_name": "Witton",
    "email": "switton6a@redcross.org",
    "gender": "Male",
    "Job-title": "Structural Engineer"
  },
  {
    "id": 228,
    "first_name": "Beverlie",
    "last_name": "Kenaway",
    "email": "bkenaway6b@myspace.com",
    "gender": "Female",
    "Job-title": "Programmer Analyst IV"
  },
  {
    "id": 229,
    "first_name": "Viole",
    "last_name": "Diegan",
    "email": "vdiegan6c@delicious.com",
    "gender": "Female",
    "Job-title": "Environmental Tech"
  },
  {
    "id": 230,
    "first_name": "Ulysses",
    "last_name": "Lazenbury",
    "email": "ulazenbury6d@ebay.com",
    "gender": "Male",
    "Job-title": "Librarian"
  },
  {
    "id": 231,
    "first_name": "Reggis",
    "last_name": "Velte",
    "email": "rvelte6e@whitehouse.gov",
    "gender": "Male",
    "Job-title": "Analog Circuit Design manager"
  },
  {
    "id": 232,
    "first_name": "Gerry",
    "last_name": "Cridland",
    "email": "gcridland6f@cnn.com",
    "gender": "Female",
    "Job-title": "Legal Assistant"
  },
  {
    "id": 233,
    "first_name": "Eduino",
    "last_name": "Morcombe",
    "email": "emorcombe6g@icio.us",
    "gender": "Male",
    "Job-title": "Sales Associate"
  },
  {
    "id": 234,
    "first_name": "Olivette",
    "last_name": "Pibworth",
    "email": "opibworth6h@soundcloud.com",
    "gender": "Female",
    "Job-title": "Software Consultant"
  },
  {
    "id": 235,
    "first_name": "Seline",
    "last_name": "McGonigle",
    "email": "smcgonigle6i@illinois.edu",
    "gender": "Female",
    "Job-title": "Electrical Engineer"
  },
  {
    "id": 236,
    "first_name": "Daryl",
    "last_name": "M'Quharge",
    "email": "dmquharge6j@wp.com",
    "gender": "Male",
    "Job-title": "Software Consultant"
  },
  {
    "id": 237,
    "first_name": "Lilyan",
    "last_name": "Rogerot",
    "email": "lrogerot6k@sbwire.com",
    "gender": "Female",
    "Job-title": "Financial Advisor"
  },
  {
    "id": 238,
    "first_name": "Horton",
    "last_name": "Dicken",
    "email": "hdicken6l@java.com",
    "gender": "Male",
    "Job-title": "Quality Control Specialist"
  },
  {
    "id": 239,
    "first_name": "Christy",
    "last_name": "O'Doghesty",
    "email": "codoghesty6m@mysql.com",
    "gender": "Male",
    "Job-title": "Senior Editor"
  },
  {
    "id": 240,
    "first_name": "Elnore",
    "last_name": "Oldale",
    "email": "eoldale6n@forbes.com",
    "gender": "Female",
    "Job-title": "VP Product Management"
  },
  {
    "id": 241,
    "first_name": "Linnet",
    "last_name": "Croome",
    "email": "lcroome6o@imageshack.us",
    "gender": "Female",
    "Job-title": "Assistant Professor"
  },
  {
    "id": 242,
    "first_name": "Carole",
    "last_name": "Mahaddie",
    "email": "cmahaddie6p@cnet.com",
    "gender": "Agender",
    "Job-title": "Speech Pathologist"
  },
  {
    "id": 243,
    "first_name": "Goober",
    "last_name": "Sabate",
    "email": "gsabate6q@microsoft.com",
    "gender": "Male",
    "Job-title": "Clinical Specialist"
  },
  {
    "id": 244,
    "first_name": "Vito",
    "last_name": "Bottoner",
    "email": "vbottoner6r@sfgate.com",
    "gender": "Male",
    "Job-title": "Civil Engineer"
  },
  {
    "id": 245,
    "first_name": "Shurlocke",
    "last_name": "Ericsson",
    "email": "sericsson6s@nyu.edu",
    "gender": "Male",
    "Job-title": "Nurse"
  },
  {
    "id": 246,
    "first_name": "Vilma",
    "last_name": "McPhaden",
    "email": "vmcphaden6t@naver.com",
    "gender": "Female",
    "Job-title": "Information Systems Manager"
  },
  {
    "id": 247,
    "first_name": "Irwin",
    "last_name": "Blackman",
    "email": "iblackman6u@baidu.com",
    "gender": "Male",
    "Job-title": "Occupational Therapist"
  },
  {
    "id": 248,
    "first_name": "Roderic",
    "last_name": "Beese",
    "email": "rbeese6v@friendfeed.com",
    "gender": "Male",
    "Job-title": "Compensation Analyst"
  },
  {
    "id": 249,
    "first_name": "Hi",
    "last_name": "Meynell",
    "email": "hmeynell6w@umich.edu",
    "gender": "Male",
    "Job-title": "Clinical Specialist"
  },
  {
    "id": 250,
    "first_name": "Terrye",
    "last_name": "Higgonet",
    "email": "thiggonet6x@fotki.com",
    "gender": "Female",
    "Job-title": "Social Worker"
  },
  {
    "id": 251,
    "first_name": "Grier",
    "last_name": "Lechelle",
    "email": "glechelle6y@moonfruit.com",
    "gender": "Female",
    "Job-title": "Budget/Accounting Analyst II"
  },
  {
    "id": 252,
    "first_name": "Lawrence",
    "last_name": "Boxe",
    "email": "lboxe6z@about.com",
    "gender": "Male",
    "Job-title": "Administrative Assistant II"
  },
  {
    "id": 253,
    "first_name": "Candida",
    "last_name": "Hightown",
    "email": "chightown70@clickbank.net",
    "gender": "Bigender",
    "Job-title": "Research Associate"
  },
  {
    "id": 254,
    "first_name": "Andrea",
    "last_name": "Pitson",
    "email": "apitson71@cnet.com",
    "gender": "Female",
    "Job-title": "VP Product Management"
  },
  {
    "id": 255,
    "first_name": "Charmion",
    "last_name": "Fairrie",
    "email": "cfairrie72@virginia.edu",
    "gender": "Female",
    "Job-title": "Developer II"
  },
  {
    "id": 256,
    "first_name": "Sharity",
    "last_name": "Fazzioli",
    "email": "sfazzioli73@youtu.be",
    "gender": "Female",
    "Job-title": "Technical Writer"
  },
  {
    "id": 257,
    "first_name": "Gerri",
    "last_name": "Partkya",
    "email": "gpartkya74@last.fm",
    "gender": "Female",
    "Job-title": "Staff Scientist"
  },
  {
    "id": 258,
    "first_name": "Devy",
    "last_name": "Ligoe",
    "email": "dligoe75@kickstarter.com",
    "gender": "Male",
    "Job-title": "VP Accounting"
  },
  {
    "id": 259,
    "first_name": "Svend",
    "last_name": "Ferrarotti",
    "email": "sferrarotti76@mozilla.org",
    "gender": "Male",
    "Job-title": "Web Developer III"
  },
  {
    "id": 260,
    "first_name": "Rafaellle",
    "last_name": "MacTrustrie",
    "email": "rmactrustrie77@walmart.com",
    "gender": "Male",
    "Job-title": "Environmental Tech"
  },
  {
    "id": 261,
    "first_name": "Dare",
    "last_name": "MacGeffen",
    "email": "dmacgeffen78@umich.edu",
    "gender": "Agender",
    "Job-title": "Nuclear Power Engineer"
  },
  {
    "id": 262,
    "first_name": "Elysha",
    "last_name": "Heckney",
    "email": "eheckney79@desdev.cn",
    "gender": "Female",
    "Job-title": "VP Product Management"
  },
  {
    "id": 263,
    "first_name": "Annissa",
    "last_name": "McRory",
    "email": "amcrory7a@ifeng.com",
    "gender": "Female",
    "Job-title": "Compensation Analyst"
  },
  {
    "id": 264,
    "first_name": "Lila",
    "last_name": "Roelvink",
    "email": "lroelvink7b@archive.org",
    "gender": "Bigender",
    "Job-title": "Product Engineer"
  },
  {
    "id": 265,
    "first_name": "Juliann",
    "last_name": "Roback",
    "email": "jroback7c@facebook.com",
    "gender": "Female",
    "Job-title": "Senior Quality Engineer"
  },
  {
    "id": 266,
    "first_name": "Ethelda",
    "last_name": "Rudgard",
    "email": "erudgard7d@dell.com",
    "gender": "Female",
    "Job-title": "Nurse Practicioner"
  },
  {
    "id": 267,
    "first_name": "Vivyan",
    "last_name": "Wingfield",
    "email": "vwingfield7e@amazon.com",
    "gender": "Female",
    "Job-title": "Computer Systems Analyst II"
  },
  {
    "id": 268,
    "first_name": "Xylina",
    "last_name": "Butlin",
    "email": "xbutlin7f@reverbnation.com",
    "gender": "Female",
    "Job-title": "Safety Technician III"
  },
  {
    "id": 269,
    "first_name": "Murdock",
    "last_name": "Gammill",
    "email": "mgammill7g@reuters.com",
    "gender": "Male",
    "Job-title": "Chemical Engineer"
  },
  {
    "id": 270,
    "first_name": "Halie",
    "last_name": "Wickersley",
    "email": "hwickersley7h@nhs.uk",
    "gender": "Female",
    "Job-title": "Environmental Tech"
  },
  {
    "id": 271,
    "first_name": "Sawyere",
    "last_name": "Bizzey",
    "email": "sbizzey7i@prnewswire.com",
    "gender": "Agender",
    "Job-title": "Accountant IV"
  },
  {
    "id": 272,
    "first_name": "Norri",
    "last_name": "Cornier",
    "email": "ncornier7j@unblog.fr",
    "gender": "Female",
    "Job-title": "Quality Engineer"
  },
  {
    "id": 273,
    "first_name": "Dorey",
    "last_name": "Lemar",
    "email": "dlemar7k@rediff.com",
    "gender": "Female",
    "Job-title": "Research Assistant II"
  },
  {
    "id": 274,
    "first_name": "Lemmie",
    "last_name": "Clutterham",
    "email": "lclutterham7l@chicagotribune.com",
    "gender": "Male",
    "Job-title": "Civil Engineer"
  },
  {
    "id": 275,
    "first_name": "Felicle",
    "last_name": "Bohler",
    "email": "fbohler7m@indiegogo.com",
    "gender": "Female",
    "Job-title": "Office Assistant I"
  },
  {
    "id": 276,
    "first_name": "Athene",
    "last_name": "Petriello",
    "email": "apetriello7n@jalbum.net",
    "gender": "Female",
    "Job-title": "Automation Specialist III"
  },
  {
    "id": 277,
    "first_name": "Flory",
    "last_name": "Wetheril",
    "email": "fwetheril7o@homestead.com",
    "gender": "Male",
    "Job-title": "Structural Analysis Engineer"
  },
  {
    "id": 278,
    "first_name": "Lek",
    "last_name": "Fessby",
    "email": "lfessby7p@adobe.com",
    "gender": "Male",
    "Job-title": "Environmental Tech"
  },
  {
    "id": 279,
    "first_name": "Clari",
    "last_name": "Irving",
    "email": "cirving7q@aboutads.info",
    "gender": "Female",
    "Job-title": "Junior Executive"
  },
  {
    "id": 280,
    "first_name": "Lena",
    "last_name": "Blacktin",
    "email": "lblacktin7r@phoca.cz",
    "gender": "Female",
    "Job-title": "Software Test Engineer I"
  },
  {
    "id": 281,
    "first_name": "Gan",
    "last_name": "O'Cridigan",
    "email": "gocridigan7s@europa.eu",
    "gender": "Male",
    "Job-title": "Social Worker"
  },
  {
    "id": 282,
    "first_name": "Bartel",
    "last_name": "Dimitrescu",
    "email": "bdimitrescu7t@delicious.com",
    "gender": "Male",
    "Job-title": "Help Desk Technician"
  },
  {
    "id": 283,
    "first_name": "Adara",
    "last_name": "Elstob",
    "email": "aelstob7u@hud.gov",
    "gender": "Agender",
    "Job-title": "Chief Design Engineer"
  },
  {
    "id": 284,
    "first_name": "Jordain",
    "last_name": "Ledster",
    "email": "jledster7v@github.com",
    "gender": "Female",
    "Job-title": "Electrical Engineer"
  },
  {
    "id": 285,
    "first_name": "Jeanne",
    "last_name": "Drillot",
    "email": "jdrillot7w@acquirethisname.com",
    "gender": "Polygender",
    "Job-title": "Information Systems Manager"
  },
  {
    "id": 286,
    "first_name": "Svend",
    "last_name": "Paolillo",
    "email": "spaolillo7x@nhs.uk",
    "gender": "Male",
    "Job-title": "Accounting Assistant IV"
  },
  {
    "id": 287,
    "first_name": "Worth",
    "last_name": "Brignell",
    "email": "wbrignell7y@over-blog.com",
    "gender": "Male",
    "Job-title": "Senior Developer"
  },
  {
    "id": 288,
    "first_name": "Shaylyn",
    "last_name": "Guidelli",
    "email": "sguidelli7z@multiply.com",
    "gender": "Female",
    "Job-title": "Design Engineer"
  },
  {
    "id": 289,
    "first_name": "Martha",
    "last_name": "Debow",
    "email": "mdebow80@wikipedia.org",
    "gender": "Polygender",
    "Job-title": "Actuary"
  },
  {
    "id": 290,
    "first_name": "Murdock",
    "last_name": "Llewelyn",
    "email": "mllewelyn81@smh.com.au",
    "gender": "Male",
    "Job-title": "Software Engineer I"
  },
  {
    "id": 291,
    "first_name": "Rosie",
    "last_name": "McCaskell",
    "email": "rmccaskell82@facebook.com",
    "gender": "Agender",
    "Job-title": "Associate Professor"
  },
  {
    "id": 292,
    "first_name": "Kimberli",
    "last_name": "Trimble",
    "email": "ktrimble83@economist.com",
    "gender": "Female",
    "Job-title": "Community Outreach Specialist"
  },
  {
    "id": 293,
    "first_name": "Iggie",
    "last_name": "Frascone",
    "email": "ifrascone84@cnet.com",
    "gender": "Male",
    "Job-title": "Senior Quality Engineer"
  },
  {
    "id": 294,
    "first_name": "Joey",
    "last_name": "Dearan",
    "email": "jdearan85@parallels.com",
    "gender": "Female",
    "Job-title": "Occupational Therapist"
  },
  {
    "id": 295,
    "first_name": "Elmo",
    "last_name": "Rojahn",
    "email": "erojahn86@reverbnation.com",
    "gender": "Genderqueer",
    "Job-title": "Computer Systems Analyst II"
  },
  {
    "id": 296,
    "first_name": "Eduard",
    "last_name": "MacRitchie",
    "email": "emacritchie87@abc.net.au",
    "gender": "Male",
    "Job-title": "Speech Pathologist"
  },
  {
    "id": 297,
    "first_name": "Horacio",
    "last_name": "Britzius",
    "email": "hbritzius88@psu.edu",
    "gender": "Male",
    "Job-title": "Analog Circuit Design manager"
  },
  {
    "id": 298,
    "first_name": "Bale",
    "last_name": "Dinnington",
    "email": "bdinnington89@reddit.com",
    "gender": "Male",
    "Job-title": "Director of Sales"
  },
  {
    "id": 299,
    "first_name": "Ingram",
    "last_name": "Renachowski",
    "email": "irenachowski8a@ning.com",
    "gender": "Male",
    "Job-title": "Quality Control Specialist"
  },
  {
    "id": 300,
    "first_name": "Fabiano",
    "last_name": "Blaskett",
    "email": "fblaskett8b@ebay.co.uk",
    "gender": "Male",
    "Job-title": "Legal Assistant"
  },
  {
    "id": 301,
    "first_name": "Cody",
    "last_name": "Du Plantier",
    "email": "cduplantier8c@seesaa.net",
    "gender": "Female",
    "Job-title": "GIS Technical Architect"
  },
  {
    "id": 302,
    "first_name": "Audi",
    "last_name": "Roussell",
    "email": "aroussell8d@imdb.com",
    "gender": "Female",
    "Job-title": "Analyst Programmer"
  },
  {
    "id": 303,
    "first_name": "Leena",
    "last_name": "Manville",
    "email": "lmanville8e@github.com",
    "gender": "Female",
    "Job-title": "Senior Developer"
  },
  {
    "id": 304,
    "first_name": "Gilburt",
    "last_name": "Leaney",
    "email": "gleaney8f@jimdo.com",
    "gender": "Bigender",
    "Job-title": "Assistant Media Planner"
  },
  {
    "id": 305,
    "first_name": "Ruth",
    "last_name": "Felkin",
    "email": "rfelkin8g@ow.ly",
    "gender": "Female",
    "Job-title": "Environmental Tech"
  },
  {
    "id": 306,
    "first_name": "Isabeau",
    "last_name": "Ragborne",
    "email": "iragborne8h@odnoklassniki.ru",
    "gender": "Female",
    "Job-title": "Payment Adjustment Coordinator"
  },
  {
    "id": 307,
    "first_name": "Celisse",
    "last_name": "Bonder",
    "email": "cbonder8i@kickstarter.com",
    "gender": "Female",
    "Job-title": "Community Outreach Specialist"
  },
  {
    "id": 308,
    "first_name": "Sanford",
    "last_name": "Dugmore",
    "email": "sdugmore8j@fastcompany.com",
    "gender": "Male",
    "Job-title": "General Manager"
  },
  {
    "id": 309,
    "first_name": "Doti",
    "last_name": "Heintsch",
    "email": "dheintsch8k@quantcast.com",
    "gender": "Female",
    "Job-title": "VP Quality Control"
  },
  {
    "id": 310,
    "first_name": "Ugo",
    "last_name": "McGlade",
    "email": "umcglade8l@biblegateway.com",
    "gender": "Male",
    "Job-title": "Compensation Analyst"
  },
  {
    "id": 311,
    "first_name": "Sibyl",
    "last_name": "Arend",
    "email": "sarend8m@dagondesign.com",
    "gender": "Female",
    "Job-title": "Research Nurse"
  },
  {
    "id": 312,
    "first_name": "Waverley",
    "last_name": "Weymouth",
    "email": "wweymouth8n@plala.or.jp",
    "gender": "Male",
    "Job-title": "Mechanical Systems Engineer"
  },
  {
    "id": 313,
    "first_name": "Doralynn",
    "last_name": "Roskell",
    "email": "droskell8o@cnbc.com",
    "gender": "Female",
    "Job-title": "Graphic Designer"
  },
  {
    "id": 314,
    "first_name": "Kaila",
    "last_name": "Causon",
    "email": "kcauson8p@ovh.net",
    "gender": "Female",
    "Job-title": "General Manager"
  },
  {
    "id": 315,
    "first_name": "Ninetta",
    "last_name": "Von Welden",
    "email": "nvonwelden8q@twitpic.com",
    "gender": "Female",
    "Job-title": "Computer Systems Analyst III"
  },
  {
    "id": 316,
    "first_name": "Henrik",
    "last_name": "Seville",
    "email": "hseville8r@loc.gov",
    "gender": "Male",
    "Job-title": "Recruiting Manager"
  },
  {
    "id": 317,
    "first_name": "Alex",
    "last_name": "Tongs",
    "email": "atongs8s@bloglines.com",
    "gender": "Male",
    "Job-title": "Geologist III"
  },
  {
    "id": 318,
    "first_name": "Gonzales",
    "last_name": "Beau",
    "email": "gbeau8t@networkadvertising.org",
    "gender": "Male",
    "Job-title": "Database Administrator II"
  },
  {
    "id": 319,
    "first_name": "Adelheid",
    "last_name": "Scholtis",
    "email": "ascholtis8u@weather.com",
    "gender": "Female",
    "Job-title": "Desktop Support Technician"
  },
  {
    "id": 320,
    "first_name": "Basil",
    "last_name": "Oseland",
    "email": "boseland8v@princeton.edu",
    "gender": "Male",
    "Job-title": "Paralegal"
  },
  {
    "id": 321,
    "first_name": "Oliviero",
    "last_name": "Illiston",
    "email": "oilliston8w@imageshack.us",
    "gender": "Male",
    "Job-title": "Legal Assistant"
  },
  {
    "id": 322,
    "first_name": "Noble",
    "last_name": "Renyard",
    "email": "nrenyard8x@unc.edu",
    "gender": "Male",
    "Job-title": "Senior Quality Engineer"
  },
  {
    "id": 323,
    "first_name": "Nicko",
    "last_name": "Croad",
    "email": "ncroad8y@cisco.com",
    "gender": "Male",
    "Job-title": "Financial Advisor"
  },
  {
    "id": 324,
    "first_name": "Evvy",
    "last_name": "Anthes",
    "email": "eanthes8z@apple.com",
    "gender": "Female",
    "Job-title": "Professor"
  },
  {
    "id": 325,
    "first_name": "Alberik",
    "last_name": "Corke",
    "email": "acorke90@joomla.org",
    "gender": "Male",
    "Job-title": "Tax Accountant"
  },
  {
    "id": 326,
    "first_name": "Janka",
    "last_name": "Moneti",
    "email": "jmoneti91@microsoft.com",
    "gender": "Female",
    "Job-title": "Engineer III"
  },
  {
    "id": 327,
    "first_name": "Blancha",
    "last_name": "Mixture",
    "email": "bmixture92@4shared.com",
    "gender": "Female",
    "Job-title": "Financial Analyst"
  },
  {
    "id": 328,
    "first_name": "Marget",
    "last_name": "Paulton",
    "email": "mpaulton93@privacy.gov.au",
    "gender": "Female",
    "Job-title": "Senior Sales Associate"
  },
  {
    "id": 329,
    "first_name": "Cynthie",
    "last_name": "Galiero",
    "email": "cgaliero94@example.com",
    "gender": "Female",
    "Job-title": "Developer I"
  },
  {
    "id": 330,
    "first_name": "Rudolf",
    "last_name": "Davidavidovics",
    "email": "rdavidavidovics95@people.com.cn",
    "gender": "Male",
    "Job-title": "Structural Analysis Engineer"
  },
  {
    "id": 331,
    "first_name": "Rolph",
    "last_name": "MacSporran",
    "email": "rmacsporran96@irs.gov",
    "gender": "Male",
    "Job-title": "Programmer Analyst II"
  },
  {
    "id": 332,
    "first_name": "Kerwin",
    "last_name": "Winterscale",
    "email": "kwinterscale97@pbs.org",
    "gender": "Male",
    "Job-title": "Financial Analyst"
  },
  {
    "id": 333,
    "first_name": "Stephan",
    "last_name": "Fleckness",
    "email": "sfleckness98@paypal.com",
    "gender": "Male",
    "Job-title": "Budget/Accounting Analyst I"
  },
  {
    "id": 334,
    "first_name": "Aurelea",
    "last_name": "Batson",
    "email": "abatson99@addthis.com",
    "gender": "Female",
    "Job-title": "Food Chemist"
  },
  {
    "id": 335,
    "first_name": "Brenda",
    "last_name": "Bradburn",
    "email": "bbradburn9a@paypal.com",
    "gender": "Female",
    "Job-title": "Sales Representative"
  },
  {
    "id": 336,
    "first_name": "Leicester",
    "last_name": "Brannigan",
    "email": "lbrannigan9b@cdc.gov",
    "gender": "Male",
    "Job-title": "Assistant Media Planner"
  },
  {
    "id": 337,
    "first_name": "Dode",
    "last_name": "Saull",
    "email": "dsaull9c@woothemes.com",
    "gender": "Female",
    "Job-title": "Dental Hygienist"
  },
  {
    "id": 338,
    "first_name": "Michel",
    "last_name": "Skillings",
    "email": "mskillings9d@uol.com.br",
    "gender": "Male",
    "Job-title": "Actuary"
  },
  {
    "id": 339,
    "first_name": "Rafaello",
    "last_name": "Jaggar",
    "email": "rjaggar9e@nbcnews.com",
    "gender": "Male",
    "Job-title": "Pharmacist"
  },
  {
    "id": 340,
    "first_name": "Betteanne",
    "last_name": "Mackerel",
    "email": "bmackerel9f@t-online.de",
    "gender": "Female",
    "Job-title": "GIS Technical Architect"
  },
  {
    "id": 341,
    "first_name": "Victor",
    "last_name": "Doneld",
    "email": "vdoneld9g@hugedomains.com",
    "gender": "Male",
    "Job-title": "Senior Financial Analyst"
  },
  {
    "id": 342,
    "first_name": "Ivett",
    "last_name": "Durtnal",
    "email": "idurtnal9h@phpbb.com",
    "gender": "Female",
    "Job-title": "Marketing Assistant"
  },
  {
    "id": 343,
    "first_name": "Clay",
    "last_name": "Eddison",
    "email": "ceddison9i@fotki.com",
    "gender": "Male",
    "Job-title": "Chemical Engineer"
  },
  {
    "id": 344,
    "first_name": "Leicester",
    "last_name": "Guttridge",
    "email": "lguttridge9j@myspace.com",
    "gender": "Male",
    "Job-title": "Safety Technician I"
  },
  {
    "id": 345,
    "first_name": "Hamel",
    "last_name": "Wissby",
    "email": "hwissby9k@miibeian.gov.cn",
    "gender": "Male",
    "Job-title": "Mechanical Systems Engineer"
  },
  {
    "id": 346,
    "first_name": "Tate",
    "last_name": "Burn",
    "email": "tburn9l@nhs.uk",
    "gender": "Female",
    "Job-title": "Business Systems Development Analyst"
  },
  {
    "id": 347,
    "first_name": "Reyna",
    "last_name": "Dorran",
    "email": "rdorran9m@wikia.com",
    "gender": "Female",
    "Job-title": "Quality Engineer"
  },
  {
    "id": 348,
    "first_name": "Alfie",
    "last_name": "Quan",
    "email": "aquan9n@miitbeian.gov.cn",
    "gender": "Male",
    "Job-title": "Assistant Media Planner"
  },
  {
    "id": 349,
    "first_name": "Benoite",
    "last_name": "Ingilson",
    "email": "bingilson9o@dagondesign.com",
    "gender": "Female",
    "Job-title": "VP Accounting"
  },
  {
    "id": 350,
    "first_name": "Francoise",
    "last_name": "Pioli",
    "email": "fpioli9p@sakura.ne.jp",
    "gender": "Female",
    "Job-title": "Nurse Practicioner"
  },
  {
    "id": 351,
    "first_name": "Dirk",
    "last_name": "Feldmark",
    "email": "dfeldmark9q@cornell.edu",
    "gender": "Male",
    "Job-title": "Help Desk Technician"
  },
  {
    "id": 352,
    "first_name": "Tawsha",
    "last_name": "Chapelhow",
    "email": "tchapelhow9r@kickstarter.com",
    "gender": "Female",
    "Job-title": "Chief Design Engineer"
  },
  {
    "id": 353,
    "first_name": "Barby",
    "last_name": "Skarin",
    "email": "bskarin9s@latimes.com",
    "gender": "Female",
    "Job-title": "VP Accounting"
  },
  {
    "id": 354,
    "first_name": "Keefe",
    "last_name": "Laurie",
    "email": "klaurie9t@squidoo.com",
    "gender": "Male",
    "Job-title": "Chemical Engineer"
  },
  {
    "id": 355,
    "first_name": "Jordana",
    "last_name": "Bachshell",
    "email": "jbachshell9u@opera.com",
    "gender": "Female",
    "Job-title": "Desktop Support Technician"
  },
  {
    "id": 356,
    "first_name": "Elle",
    "last_name": "Bigglestone",
    "email": "ebigglestone9v@go.com",
    "gender": "Non-binary",
    "Job-title": "Registered Nurse"
  },
  {
    "id": 357,
    "first_name": "Evaleen",
    "last_name": "Heathorn",
    "email": "eheathorn9w@reuters.com",
    "gender": "Female",
    "Job-title": "Social Worker"
  },
  {
    "id": 358,
    "first_name": "Pollyanna",
    "last_name": "Capron",
    "email": "pcapron9x@friendfeed.com",
    "gender": "Female",
    "Job-title": "Pharmacist"
  },
  {
    "id": 359,
    "first_name": "Vladamir",
    "last_name": "Hunn",
    "email": "vhunn9y@last.fm",
    "gender": "Male",
    "Job-title": "Junior Executive"
  },
  {
    "id": 360,
    "first_name": "Harrison",
    "last_name": "Meneo",
    "email": "hmeneo9z@usatoday.com",
    "gender": "Male",
    "Job-title": "Registered Nurse"
  },
  {
    "id": 361,
    "first_name": "Fannie",
    "last_name": "Burgis",
    "email": "fburgisa0@behance.net",
    "gender": "Female",
    "Job-title": "Teacher"
  },
  {
    "id": 362,
    "first_name": "Charisse",
    "last_name": "D'Arrigo",
    "email": "cdarrigoa1@aboutads.info",
    "gender": "Female",
    "Job-title": "Software Test Engineer IV"
  },
  {
    "id": 363,
    "first_name": "Avie",
    "last_name": "Trusler",
    "email": "atruslera2@blog.com",
    "gender": "Female",
    "Job-title": "Quality Control Specialist"
  },
  {
    "id": 364,
    "first_name": "Emmerich",
    "last_name": "Bryning",
    "email": "ebryninga3@domainmarket.com",
    "gender": "Male",
    "Job-title": "Software Consultant"
  },
  {
    "id": 365,
    "first_name": "Hurley",
    "last_name": "Dami",
    "email": "hdamia4@twitter.com",
    "gender": "Male",
    "Job-title": "Research Nurse"
  },
  {
    "id": 366,
    "first_name": "Mortie",
    "last_name": "McLanachan",
    "email": "mmclanachana5@wp.com",
    "gender": "Agender",
    "Job-title": "VP Marketing"
  },
  {
    "id": 367,
    "first_name": "Ara",
    "last_name": "Thornton",
    "email": "athorntona6@exblog.jp",
    "gender": "Male",
    "Job-title": "Statistician II"
  },
  {
    "id": 368,
    "first_name": "Hurlee",
    "last_name": "Bester",
    "email": "hbestera7@wired.com",
    "gender": "Male",
    "Job-title": "Programmer II"
  },
  {
    "id": 369,
    "first_name": "Margarethe",
    "last_name": "Oswal",
    "email": "moswala8@amazon.co.jp",
    "gender": "Female",
    "Job-title": "Financial Analyst"
  },
  {
    "id": 370,
    "first_name": "Wilbert",
    "last_name": "Footitt",
    "email": "wfootitta9@thetimes.co.uk",
    "gender": "Male",
    "Job-title": "Recruiter"
  },
  {
    "id": 371,
    "first_name": "Brod",
    "last_name": "Raunds",
    "email": "braundsaa@opensource.org",
    "gender": "Male",
    "Job-title": "Financial Advisor"
  },
  {
    "id": 372,
    "first_name": "Clarisse",
    "last_name": "Flaunier",
    "email": "cflaunierab@a8.net",
    "gender": "Female",
    "Job-title": "Recruiting Manager"
  },
  {
    "id": 373,
    "first_name": "Kevon",
    "last_name": "Dreng",
    "email": "kdrengac@who.int",
    "gender": "Male",
    "Job-title": "Dental Hygienist"
  },
  {
    "id": 374,
    "first_name": "Darlene",
    "last_name": "Veivers",
    "email": "dveiversad@examiner.com",
    "gender": "Female",
    "Job-title": "Assistant Professor"
  },
  {
    "id": 375,
    "first_name": "Paulette",
    "last_name": "Taaffe",
    "email": "ptaaffeae@ca.gov",
    "gender": "Female",
    "Job-title": "Assistant Manager"
  },
  {
    "id": 376,
    "first_name": "Kirby",
    "last_name": "Hearley",
    "email": "khearleyaf@whitehouse.gov",
    "gender": "Male",
    "Job-title": "Budget/Accounting Analyst IV"
  },
  {
    "id": 377,
    "first_name": "Guillema",
    "last_name": "Wauchope",
    "email": "gwauchopeag@drupal.org",
    "gender": "Female",
    "Job-title": "Budget/Accounting Analyst II"
  },
  {
    "id": 378,
    "first_name": "Rees",
    "last_name": "Cadamy",
    "email": "rcadamyah@vistaprint.com",
    "gender": "Male",
    "Job-title": "Account Representative III"
  },
  {
    "id": 379,
    "first_name": "Marwin",
    "last_name": "Tackes",
    "email": "mtackesai@tmall.com",
    "gender": "Male",
    "Job-title": "Chief Design Engineer"
  },
  {
    "id": 380,
    "first_name": "Antonin",
    "last_name": "Barnicott",
    "email": "abarnicottaj@surveymonkey.com",
    "gender": "Male",
    "Job-title": "Graphic Designer"
  },
  {
    "id": 381,
    "first_name": "Otis",
    "last_name": "Glenn",
    "email": "oglennak@statcounter.com",
    "gender": "Male",
    "Job-title": "Speech Pathologist"
  },
  {
    "id": 382,
    "first_name": "Veronica",
    "last_name": "Folbigg",
    "email": "vfolbiggal@abc.net.au",
    "gender": "Female",
    "Job-title": "Statistician II"
  },
  {
    "id": 383,
    "first_name": "Page",
    "last_name": "Moizer",
    "email": "pmoizeram@tiny.cc",
    "gender": "Female",
    "Job-title": "Design Engineer"
  },
  {
    "id": 384,
    "first_name": "Barbie",
    "last_name": "Cuncarr",
    "email": "bcuncarran@multiply.com",
    "gender": "Female",
    "Job-title": "Marketing Manager"
  },
  {
    "id": 385,
    "first_name": "Dagny",
    "last_name": "Pizzey",
    "email": "dpizzeyao@google.de",
    "gender": "Non-binary",
    "Job-title": "Web Designer II"
  },
  {
    "id": 386,
    "first_name": "Hetty",
    "last_name": "Manger",
    "email": "hmangerap@last.fm",
    "gender": "Female",
    "Job-title": "Assistant Professor"
  },
  {
    "id": 387,
    "first_name": "Jerrie",
    "last_name": "McReynolds",
    "email": "jmcreynoldsaq@oracle.com",
    "gender": "Male",
    "Job-title": "Environmental Tech"
  },
  {
    "id": 388,
    "first_name": "Ric",
    "last_name": "Rawood",
    "email": "rrawoodar@google.es",
    "gender": "Male",
    "Job-title": "Graphic Designer"
  },
  {
    "id": 389,
    "first_name": "Leshia",
    "last_name": "Vasyushkhin",
    "email": "lvasyushkhinas@bloomberg.com",
    "gender": "Female",
    "Job-title": "Software Test Engineer III"
  },
  {
    "id": 390,
    "first_name": "Bethina",
    "last_name": "McGlaughn",
    "email": "bmcglaughnat@mapy.cz",
    "gender": "Female",
    "Job-title": "Structural Engineer"
  },
  {
    "id": 391,
    "first_name": "Ellynn",
    "last_name": "Files",
    "email": "efilesau@4shared.com",
    "gender": "Agender",
    "Job-title": "VP Product Management"
  },
  {
    "id": 392,
    "first_name": "Thurstan",
    "last_name": "Caldicott",
    "email": "tcaldicottav@51.la",
    "gender": "Male",
    "Job-title": "Librarian"
  },
  {
    "id": 393,
    "first_name": "Nicoli",
    "last_name": "Satterley",
    "email": "nsatterleyaw@ucla.edu",
    "gender": "Female",
    "Job-title": "Director of Sales"
  },
  {
    "id": 394,
    "first_name": "Pennie",
    "last_name": "Minor",
    "email": "pminorax@webmd.com",
    "gender": "Female",
    "Job-title": "Assistant Professor"
  },
  {
    "id": 395,
    "first_name": "Kristel",
    "last_name": "Docker",
    "email": "kdockeray@deliciousdays.com",
    "gender": "Female",
    "Job-title": "Programmer Analyst IV"
  },
  {
    "id": 396,
    "first_name": "Patsy",
    "last_name": "Piatkowski",
    "email": "ppiatkowskiaz@spiegel.de",
    "gender": "Male",
    "Job-title": "Chemical Engineer"
  },
  {
    "id": 397,
    "first_name": "Fritz",
    "last_name": "Heales",
    "email": "fhealesb0@mysql.com",
    "gender": "Male",
    "Job-title": "Sales Representative"
  },
  {
    "id": 398,
    "first_name": "Aeriela",
    "last_name": "Polglase",
    "email": "apolglaseb1@examiner.com",
    "gender": "Female",
    "Job-title": "Accounting Assistant III"
  },
  {
    "id": 399,
    "first_name": "Devy",
    "last_name": "Smithson",
    "email": "dsmithsonb2@virginia.edu",
    "gender": "Male",
    "Job-title": "Occupational Therapist"
  },
  {
    "id": 400,
    "first_name": "Bailie",
    "last_name": "Fritzer",
    "email": "bfritzerb3@deliciousdays.com",
    "gender": "Male",
    "Job-title": "Research Assistant IV"
  },
  {
    "id": 401,
    "first_name": "Eugenia",
    "last_name": "Vesco",
    "email": "evescob4@bravesites.com",
    "gender": "Female",
    "Job-title": "Environmental Specialist"
  },
  {
    "id": 402,
    "first_name": "Kacy",
    "last_name": "Wholesworth",
    "email": "kwholesworthb5@shop-pro.jp",
    "gender": "Female",
    "Job-title": "Health Coach III"
  },
  {
    "id": 403,
    "first_name": "Antonella",
    "last_name": "Phizaclea",
    "email": "aphizacleab6@ebay.co.uk",
    "gender": "Female",
    "Job-title": "Speech Pathologist"
  },
  {
    "id": 404,
    "first_name": "Daryl",
    "last_name": "Millen",
    "email": "dmillenb7@salon.com",
    "gender": "Genderqueer",
    "Job-title": "Office Assistant III"
  },
  {
    "id": 405,
    "first_name": "Darby",
    "last_name": "Coventry",
    "email": "dcoventryb8@sciencedirect.com",
    "gender": "Female",
    "Job-title": "Analyst Programmer"
  },
  {
    "id": 406,
    "first_name": "Pooh",
    "last_name": "Twelvetree",
    "email": "ptwelvetreeb9@redcross.org",
    "gender": "Bigender",
    "Job-title": "Nurse"
  },
  {
    "id": 407,
    "first_name": "Elva",
    "last_name": "Grindley",
    "email": "egrindleyba@reference.com",
    "gender": "Female",
    "Job-title": "Research Associate"
  },
  {
    "id": 408,
    "first_name": "Vallie",
    "last_name": "Monckton",
    "email": "vmoncktonbb@1und1.de",
    "gender": "Female",
    "Job-title": "Research Associate"
  },
  {
    "id": 409,
    "first_name": "Winifield",
    "last_name": "Partleton",
    "email": "wpartletonbc@ed.gov",
    "gender": "Male",
    "Job-title": "Social Worker"
  },
  {
    "id": 410,
    "first_name": "Leland",
    "last_name": "Carlton",
    "email": "lcarltonbd@infoseek.co.jp",
    "gender": "Male",
    "Job-title": "Computer Systems Analyst II"
  },
  {
    "id": 411,
    "first_name": "Elbertina",
    "last_name": "Kleinsinger",
    "email": "ekleinsingerbe@mapquest.com",
    "gender": "Female",
    "Job-title": "VP Accounting"
  },
  {
    "id": 412,
    "first_name": "Shelagh",
    "last_name": "Picard",
    "email": "spicardbf@mlb.com",
    "gender": "Female",
    "Job-title": "Occupational Therapist"
  },
  {
    "id": 413,
    "first_name": "Clark",
    "last_name": "Pointing",
    "email": "cpointingbg@google.cn",
    "gender": "Male",
    "Job-title": "Nuclear Power Engineer"
  },
  {
    "id": 414,
    "first_name": "Clo",
    "last_name": "Soper",
    "email": "csoperbh@jiathis.com",
    "gender": "Female",
    "Job-title": "Geological Engineer"
  },
  {
    "id": 415,
    "first_name": "Gayelord",
    "last_name": "Shackell",
    "email": "gshackellbi@msn.com",
    "gender": "Male",
    "Job-title": "Assistant Professor"
  },
  {
    "id": 416,
    "first_name": "Bartlet",
    "last_name": "Braniff",
    "email": "bbraniffbj@godaddy.com",
    "gender": "Agender",
    "Job-title": "Product Engineer"
  },
  {
    "id": 417,
    "first_name": "Aura",
    "last_name": "Aimeric",
    "email": "aaimericbk@gizmodo.com",
    "gender": "Female",
    "Job-title": "Biostatistician I"
  },
  {
    "id": 418,
    "first_name": "Paige",
    "last_name": "Banat",
    "email": "pbanatbl@weather.com",
    "gender": "Male",
    "Job-title": "Assistant Media Planner"
  },
  {
    "id": 419,
    "first_name": "Mildrid",
    "last_name": "Denmead",
    "email": "mdenmeadbm@histats.com",
    "gender": "Genderfluid",
    "Job-title": "Accounting Assistant III"
  },
  {
    "id": 420,
    "first_name": "Josh",
    "last_name": "Jervoise",
    "email": "jjervoisebn@seesaa.net",
    "gender": "Male",
    "Job-title": "Senior Developer"
  },
  {
    "id": 421,
    "first_name": "Kittie",
    "last_name": "Iveson",
    "email": "kivesonbo@youtube.com",
    "gender": "Female",
    "Job-title": "Chemical Engineer"
  },
  {
    "id": 422,
    "first_name": "Augustine",
    "last_name": "Ivanchikov",
    "email": "aivanchikovbp@reddit.com",
    "gender": "Polygender",
    "Job-title": "VP Quality Control"
  },
  {
    "id": 423,
    "first_name": "Farah",
    "last_name": "Bowton",
    "email": "fbowtonbq@flavors.me",
    "gender": "Female",
    "Job-title": "Financial Advisor"
  },
  {
    "id": 424,
    "first_name": "Cybil",
    "last_name": "Prestage",
    "email": "cprestagebr@walmart.com",
    "gender": "Female",
    "Job-title": "Biostatistician I"
  },
  {
    "id": 425,
    "first_name": "Michaelina",
    "last_name": "Dowdeswell",
    "email": "mdowdeswellbs@auda.org.au",
    "gender": "Female",
    "Job-title": "Nurse"
  },
  {
    "id": 426,
    "first_name": "Sylvester",
    "last_name": "Messam",
    "email": "smessambt@paypal.com",
    "gender": "Male",
    "Job-title": "Senior Cost Accountant"
  },
  {
    "id": 427,
    "first_name": "Katlin",
    "last_name": "Shippey",
    "email": "kshippeybu@wisc.edu",
    "gender": "Female",
    "Job-title": "Recruiting Manager"
  },
  {
    "id": 428,
    "first_name": "Ban",
    "last_name": "Sachno",
    "email": "bsachnobv@globo.com",
    "gender": "Male",
    "Job-title": "Chief Design Engineer"
  },
  {
    "id": 429,
    "first_name": "Annmaria",
    "last_name": "Tootin",
    "email": "atootinbw@weibo.com",
    "gender": "Female",
    "Job-title": "Research Nurse"
  },
  {
    "id": 430,
    "first_name": "Natalya",
    "last_name": "Baytrop",
    "email": "nbaytropbx@illinois.edu",
    "gender": "Female",
    "Job-title": "VP Marketing"
  },
  {
    "id": 431,
    "first_name": "Wittie",
    "last_name": "Loosemore",
    "email": "wloosemoreby@cafepress.com",
    "gender": "Male",
    "Job-title": "Business Systems Development Analyst"
  },
  {
    "id": 432,
    "first_name": "Gwennie",
    "last_name": "Dungey",
    "email": "gdungeybz@fda.gov",
    "gender": "Non-binary",
    "Job-title": "Account Coordinator"
  },
  {
    "id": 433,
    "first_name": "Terra",
    "last_name": "Baggallay",
    "email": "tbaggallayc0@tuttocitta.it",
    "gender": "Female",
    "Job-title": "Assistant Professor"
  },
  {
    "id": 434,
    "first_name": "Cloris",
    "last_name": "Hassell",
    "email": "chassellc1@tamu.edu",
    "gender": "Female",
    "Job-title": "Web Developer II"
  },
  {
    "id": 435,
    "first_name": "Krissy",
    "last_name": "Sachno",
    "email": "ksachnoc2@theglobeandmail.com",
    "gender": "Female",
    "Job-title": "Recruiting Manager"
  },
  {
    "id": 436,
    "first_name": "Dewey",
    "last_name": "Waberer",
    "email": "dwabererc3@blinklist.com",
    "gender": "Male",
    "Job-title": "Operator"
  },
  {
    "id": 437,
    "first_name": "Maisey",
    "last_name": "Lafay",
    "email": "mlafayc4@sciencedirect.com",
    "gender": "Female",
    "Job-title": "General Manager"
  },
  {
    "id": 438,
    "first_name": "Sigrid",
    "last_name": "Tupper",
    "email": "stupperc5@opera.com",
    "gender": "Female",
    "Job-title": "Executive Secretary"
  },
  {
    "id": 439,
    "first_name": "Clare",
    "last_name": "Crouse",
    "email": "ccrousec6@hostgator.com",
    "gender": "Female",
    "Job-title": "Community Outreach Specialist"
  },
  {
    "id": 440,
    "first_name": "Mateo",
    "last_name": "Kynett",
    "email": "mkynettc7@list-manage.com",
    "gender": "Polygender",
    "Job-title": "Analyst Programmer"
  },
  {
    "id": 441,
    "first_name": "Sibley",
    "last_name": "Perroni",
    "email": "sperronic8@abc.net.au",
    "gender": "Female",
    "Job-title": "Quality Control Specialist"
  },
  {
    "id": 442,
    "first_name": "Rodolfo",
    "last_name": "Ovise",
    "email": "rovisec9@gov.uk",
    "gender": "Male",
    "Job-title": "Clinical Specialist"
  },
  {
    "id": 443,
    "first_name": "Emmanuel",
    "last_name": "Lavelle",
    "email": "elavelleca@cocolog-nifty.com",
    "gender": "Male",
    "Job-title": "VP Quality Control"
  },
  {
    "id": 444,
    "first_name": "Glen",
    "last_name": "Pawellek",
    "email": "gpawellekcb@mac.com",
    "gender": "Male",
    "Job-title": "Systems Administrator I"
  },
  {
    "id": 445,
    "first_name": "Alaric",
    "last_name": "Kippie",
    "email": "akippiecc@quantcast.com",
    "gender": "Male",
    "Job-title": "Assistant Professor"
  },
  {
    "id": 446,
    "first_name": "Alysia",
    "last_name": "Salvadori",
    "email": "asalvadoricd@ustream.tv",
    "gender": "Female",
    "Job-title": "Design Engineer"
  },
  {
    "id": 447,
    "first_name": "Krishna",
    "last_name": "Mordy",
    "email": "kmordyce@google.co.jp",
    "gender": "Male",
    "Job-title": "Mechanical Systems Engineer"
  },
  {
    "id": 448,
    "first_name": "Cahra",
    "last_name": "Forder",
    "email": "cfordercf@merriam-webster.com",
    "gender": "Female",
    "Job-title": "Recruiting Manager"
  },
  {
    "id": 449,
    "first_name": "Amargo",
    "last_name": "Schade",
    "email": "aschadecg@addtoany.com",
    "gender": "Female",
    "Job-title": "Software Test Engineer IV"
  },
  {
    "id": 450,
    "first_name": "Arther",
    "last_name": "MacAdam",
    "email": "amacadamch@themeforest.net",
    "gender": "Male",
    "Job-title": "Geological Engineer"
  },
  {
    "id": 451,
    "first_name": "Tabbi",
    "last_name": "Clarae",
    "email": "tclaraeci@amazon.com",
    "gender": "Female",
    "Job-title": "Programmer II"
  },
  {
    "id": 452,
    "first_name": "Barrie",
    "last_name": "Henzley",
    "email": "bhenzleycj@army.mil",
    "gender": "Male",
    "Job-title": "Database Administrator I"
  },
  {
    "id": 453,
    "first_name": "Emeline",
    "last_name": "Derell",
    "email": "ederellck@amazonaws.com",
    "gender": "Female",
    "Job-title": "VP Quality Control"
  },
  {
    "id": 454,
    "first_name": "Fowler",
    "last_name": "Hainning",
    "email": "fhainningcl@chronoengine.com",
    "gender": "Male",
    "Job-title": "Engineer III"
  },
  {
    "id": 455,
    "first_name": "Pooh",
    "last_name": "Farady",
    "email": "pfaradycm@flavors.me",
    "gender": "Female",
    "Job-title": "Financial Advisor"
  },
  {
    "id": 456,
    "first_name": "Tadeo",
    "last_name": "Cordery",
    "email": "tcorderycn@mail.ru",
    "gender": "Male",
    "Job-title": "Professor"
  },
  {
    "id": 457,
    "first_name": "Kimberli",
    "last_name": "Jefferd",
    "email": "kjefferdco@vistaprint.com",
    "gender": "Female",
    "Job-title": "Analyst Programmer"
  },
  {
    "id": 458,
    "first_name": "Sebastiano",
    "last_name": "Bradnick",
    "email": "sbradnickcp@tripod.com",
    "gender": "Male",
    "Job-title": "Senior Developer"
  },
  {
    "id": 459,
    "first_name": "Sibylla",
    "last_name": "Van Der Vlies",
    "email": "svandervliescq@apache.org",
    "gender": "Female",
    "Job-title": "Graphic Designer"
  },
  {
    "id": 460,
    "first_name": "Luciana",
    "last_name": "Mc Caghan",
    "email": "lmccaghancr@nyu.edu",
    "gender": "Female",
    "Job-title": "Business Systems Development Analyst"
  },
  {
    "id": 461,
    "first_name": "Gerome",
    "last_name": "Balcombe",
    "email": "gbalcombecs@blogspot.com",
    "gender": "Male",
    "Job-title": "Automation Specialist III"
  },
  {
    "id": 462,
    "first_name": "Heindrick",
    "last_name": "Wingham",
    "email": "hwinghamct@technorati.com",
    "gender": "Male",
    "Job-title": "Senior Developer"
  },
  {
    "id": 463,
    "first_name": "Fernanda",
    "last_name": "Screaton",
    "email": "fscreatoncu@adobe.com",
    "gender": "Female",
    "Job-title": "Chemical Engineer"
  },
  {
    "id": 464,
    "first_name": "Matthias",
    "last_name": "Entwisle",
    "email": "mentwislecv@clickbank.net",
    "gender": "Male",
    "Job-title": "Senior Editor"
  },
  {
    "id": 465,
    "first_name": "Annette",
    "last_name": "Gobeaux",
    "email": "agobeauxcw@illinois.edu",
    "gender": "Female",
    "Job-title": "Human Resources Assistant III"
  },
  {
    "id": 466,
    "first_name": "Angel",
    "last_name": "Kenway",
    "email": "akenwaycx@cornell.edu",
    "gender": "Male",
    "Job-title": "Analyst Programmer"
  },
  {
    "id": 467,
    "first_name": "Niccolo",
    "last_name": "Neumann",
    "email": "nneumanncy@accuweather.com",
    "gender": "Male",
    "Job-title": "Recruiter"
  },
  {
    "id": 468,
    "first_name": "Janie",
    "last_name": "Castlake",
    "email": "jcastlakecz@purevolume.com",
    "gender": "Female",
    "Job-title": "Nurse"
  },
  {
    "id": 469,
    "first_name": "Dayle",
    "last_name": "Bosanko",
    "email": "dbosankod0@wordpress.org",
    "gender": "Female",
    "Job-title": "Desktop Support Technician"
  },
  {
    "id": 470,
    "first_name": "Amby",
    "last_name": "Linstead",
    "email": "alinsteadd1@deliciousdays.com",
    "gender": "Male",
    "Job-title": "Speech Pathologist"
  },
  {
    "id": 471,
    "first_name": "Blinny",
    "last_name": "Fonquernie",
    "email": "bfonquernied2@si.edu",
    "gender": "Female",
    "Job-title": "VP Quality Control"
  },
  {
    "id": 472,
    "first_name": "Tamarah",
    "last_name": "Aitken",
    "email": "taitkend3@desdev.cn",
    "gender": "Female",
    "Job-title": "Programmer Analyst III"
  },
  {
    "id": 473,
    "first_name": "Lorenza",
    "last_name": "Binnell",
    "email": "lbinnelld4@typepad.com",
    "gender": "Female",
    "Job-title": "Geologist I"
  },
  {
    "id": 474,
    "first_name": "Mack",
    "last_name": "Fensome",
    "email": "mfensomed5@wiley.com",
    "gender": "Male",
    "Job-title": "Actuary"
  },
  {
    "id": 475,
    "first_name": "Giordano",
    "last_name": "Pettinger",
    "email": "gpettingerd6@squidoo.com",
    "gender": "Male",
    "Job-title": "Civil Engineer"
  },
  {
    "id": 476,
    "first_name": "Devland",
    "last_name": "Maxwaile",
    "email": "dmaxwailed7@issuu.com",
    "gender": "Male",
    "Job-title": "Automation Specialist I"
  },
  {
    "id": 477,
    "first_name": "Nola",
    "last_name": "Keward",
    "email": "nkewardd8@yale.edu",
    "gender": "Female",
    "Job-title": "Research Assistant IV"
  },
  {
    "id": 478,
    "first_name": "Jacintha",
    "last_name": "Beatens",
    "email": "jbeatensd9@360.cn",
    "gender": "Female",
    "Job-title": "Computer Systems Analyst IV"
  },
  {
    "id": 479,
    "first_name": "Fina",
    "last_name": "Barkus",
    "email": "fbarkusda@google.cn",
    "gender": "Female",
    "Job-title": "Office Assistant III"
  },
  {
    "id": 480,
    "first_name": "Elizabeth",
    "last_name": "Herrero",
    "email": "eherrerodb@state.gov",
    "gender": "Female",
    "Job-title": "Business Systems Development Analyst"
  },
  {
    "id": 481,
    "first_name": "Constantin",
    "last_name": "Coots",
    "email": "ccootsdc@studiopress.com",
    "gender": "Male",
    "Job-title": "Research Nurse"
  },
  {
    "id": 482,
    "first_name": "Dulcy",
    "last_name": "de Quesne",
    "email": "ddequesnedd@rambler.ru",
    "gender": "Female",
    "Job-title": "Occupational Therapist"
  },
  {
    "id": 483,
    "first_name": "Ruthy",
    "last_name": "Lembcke",
    "email": "rlembckede@netscape.com",
    "gender": "Genderqueer",
    "Job-title": "Cost Accountant"
  },
  {
    "id": 484,
    "first_name": "Corrianne",
    "last_name": "Brettel",
    "email": "cbretteldf@oaic.gov.au",
    "gender": "Female",
    "Job-title": "VP Marketing"
  },
  {
    "id": 485,
    "first_name": "Kathe",
    "last_name": "Pie",
    "email": "kpiedg@rakuten.co.jp",
    "gender": "Female",
    "Job-title": "Research Nurse"
  },
  {
    "id": 486,
    "first_name": "Bebe",
    "last_name": "Dear",
    "email": "bdeardh@examiner.com",
    "gender": "Female",
    "Job-title": "Software Test Engineer II"
  },
  {
    "id": 487,
    "first_name": "Rolf",
    "last_name": "Worham",
    "email": "rworhamdi@wordpress.org",
    "gender": "Male",
    "Job-title": "Account Executive"
  },
  {
    "id": 488,
    "first_name": "Hermie",
    "last_name": "Bouldon",
    "email": "hbouldondj@wordpress.com",
    "gender": "Male",
    "Job-title": "Dental Hygienist"
  },
  {
    "id": 489,
    "first_name": "Ephrem",
    "last_name": "Cicchinelli",
    "email": "ecicchinellidk@networkadvertising.org",
    "gender": "Male",
    "Job-title": "Environmental Tech"
  },
  {
    "id": 490,
    "first_name": "Axel",
    "last_name": "Kiefer",
    "email": "akieferdl@house.gov",
    "gender": "Male",
    "Job-title": "VP Accounting"
  },
  {
    "id": 491,
    "first_name": "Zea",
    "last_name": "Locock",
    "email": "zlocockdm@merriam-webster.com",
    "gender": "Genderfluid",
    "Job-title": "Account Representative III"
  },
  {
    "id": 492,
    "first_name": "Skelly",
    "last_name": "Roy",
    "email": "sroydn@slideshare.net",
    "gender": "Male",
    "Job-title": "Help Desk Operator"
  },
  {
    "id": 493,
    "first_name": "Mead",
    "last_name": "Yakunin",
    "email": "myakunindo@sciencedaily.com",
    "gender": "Female",
    "Job-title": "Community Outreach Specialist"
  },
  {
    "id": 494,
    "first_name": "Asa",
    "last_name": "Bellino",
    "email": "abellinodp@about.me",
    "gender": "Male",
    "Job-title": "Registered Nurse"
  },
  {
    "id": 495,
    "first_name": "Pennie",
    "last_name": "Filipychev",
    "email": "pfilipychevdq@dedecms.com",
    "gender": "Female",
    "Job-title": "Account Representative IV"
  },
  {
    "id": 496,
    "first_name": "Mata",
    "last_name": "Fiorentino",
    "email": "mfiorentinodr@go.com",
    "gender": "Male",
    "Job-title": "Statistician III"
  },
  {
    "id": 497,
    "first_name": "Dyanna",
    "last_name": "Bogays",
    "email": "dbogaysds@auda.org.au",
    "gender": "Female",
    "Job-title": "Chief Design Engineer"
  },
  {
    "id": 498,
    "first_name": "Natividad",
    "last_name": "Izakof",
    "email": "nizakofdt@cam.ac.uk",
    "gender": "Agender",
    "Job-title": "Paralegal"
  },
  {
    "id": 499,
    "first_name": "Lissa",
    "last_name": "Stealfox",
    "email": "lstealfoxdu@oracle.com",
    "gender": "Female",
    "Job-title": "Speech Pathologist"
  },
  {
    "id": 500,
    "first_name": "Charmane",
    "last_name": "Fransson",
    "email": "cfranssondv@miitbeian.gov.cn",
    "gender": "Female",
    "Job-title": "Project Manager"
  },
  {
    "first_name": "Dhiraj",
    "last_name": "Patil",
    "email": "dhiraj.com",
    "gender": "male",
    "id": 501
  },
  {
    "first_name": "Dhiraj",
    "last_name": "Patil",
    "email": "dhiraj.com",
    "gender": "male",
    "id": 502
  }
]
